Workbook
Name Slicer_Gender: #N/A
Name Slicer_Order_Date: #N/A
Name Slicer_Payment_Type: #N/A
Name Slicer_Product_Category: #N/A
Name Slicer_Store_City: #N/A
Name Slicer_Store_City1: #N/A
Name Slicer_Store_type: #N/A

Sheet Customer_Dim
A1: Customer_ID | B1: Name | C1: Age | D1: Gender | E1: City | F1: State | G1: Country | H1: Loyalty_Level
A2: CUST1000 | B2: sheena bonilla | C2: 55 | D2: Male | E2: Donaldton | F2: North Carolina | G2: USA
A3: CUST1001 | B3: Eugene Nelson | C3: 26 | D3: Female | E3: Phillipsmouth | F3: North Dakota | G3: USA | H3: Platinum
A4: CUST1002 | B4: dr. Benjamin Price | C4: 29 | D4: Female | E4: Kylebury | F4: Alabama | G4: USA | H4: Platinum
A5: CUST1003 | B5: jeremy harris | C5: 59 | D5: Female | E5: Thomastown | F5: Ohio | G5: USA | H5: Bronze
A6: CUST1004 | B6: Caroline Collins | C6: 64 | D6: Female | E6: Nicholasshire | F6: California | G6: USA | H6: Silver
A7: CUST1005 | B7: Christine Vaughn | C7: 24 | D7: Male | E7: East Amandamouth | F7: Oregon | G7: USA | H7: Bronze
A8: CUST1006 | B8: Amber Jackson | C8: 29 | D8: Female | E8: Deborahborough | F8: South Dakota | G8: USA | H8: Platinum
A9: CUST1007 | B9: Daniel Boyd | C9: 29 | D9: Female | E9: West Pamelafurt | F9: West Virginia | G9: USA | H9: Bronze
A10: CUST1008 | B10: Melissa Howard | C10: 53 | D10: Female | E10: Maynardton | F10: New Hampshire | G10: USA | H10: Gold
A11: CUST1009 | B11: Ms. Maria Leach | C11: 64 | D11: Male | E11: Melissashire | F11: Pennsylvania | G11: USA | H11: Platinum
A12: CUST1010 | B12: Dominic Page | C12: 53 | D12: Male | E12: Port Michaelburgh | F12: Pennsylvania | G12: USA | H12: Bronze
A13: CUST1011 | B13: Brian Lopez | C13: 28 | D13: Female | E13: East Krista | F13: New York | G13: USA | H13: Gold
A14: CUST1012 | B14: Kenneth Lambert | C14: 55 | D14: Female | E14: North Kathryn | F14: Kansas | G14: USA | H14: Platinum
... A19: CUST1017 | B19: Adam Cruz | C19: 60 | D19: Female | E19: Brandonville | F19: Georgia | G19: USA | H19: Platinum
A20: CUST1018 | B20: Rhonda Moss | C20: 43 | D20: Male | E20: South William | F20: Kansas | G20: USA
A21: CUST1019 | B21: Michael Torres | C21: 46 | D21: Female | E21: Gonzalezfort | F21: New Jersey | G21: USA | H21: Platinum
A22: CUST1020 | B22: Bridget Allen | C22: 59 | D22: Male | E22: Lake Shaneburgh | F22: Delaware | G22: USA | H22: Silver
A23: CUST1021 | B23: Jeff Martinez | C23: 36 | D23: Female | E23: Smithburgh | F23: Oklahoma | G23: USA | H23: Gold
A24: CUST1022 | B24: paul fox | C24: 33 | D24: Female | E24: Michaelton | F24: Hawaii | G24: USA | H24: Silver
A25: CUST1023 | B25: Jonathan Steele | C25: 52 | D25: Female | E25: Molinabury | F25: Oregon | G25: USA | H25: Silver
A26: CUST1024 | B26: Heather Collins | C26: 40 | D26: Male | E26: Rogerschester | F26: Idaho | G26: USA | H26: Platinum
A27: CUST1025 | B27: Diana Taylor | C27: 59 | D27: Female | E27: Vasqueztown | F27: California | G27: USA | H27: Bronze
A28: CUST1026 | B28: Amber Carlson | C28: 18 | D28: Female | E28: East Michellemouth | F28: Missouri | G28: USA | H28: Gold
A29: CUST1027 | B29: Leslie Johnson | C29: 31 | D29: Male | E29: Mollyshire | F29: Utah | G29: USA
A30: CUST1028 | B30: Joshua Ryan | C30: 27 | D30: Female | E30: New David | F30: New Jersey | G30: USA | H30: Platinum
A31: CUST1029 | B31: David Arnold | C31: 54 | D31: Female | E31: East Jennifer | F31: California | G31: USA | H31: Silver
A32: CUST1030 | B32: Jessica Acevedo | C32: 64 | D32: Female | E32: Amybury | F32: Pennsylvania | G32: USA | H32: Bronze
A33: CUST1031 | B33: Sarah Vance | C33: 41 | D33: Male | E33: Johnsonville | F33: Oregon | G33: USA | H33: Silver
A34: CUST1032 | B34: Mike Jennings | C34: 48 | D34: Female | E34: Fostermouth | F34: Arizona | G34: USA | H34: Gold
A35: CUST1033 | B35: Robert Jones DDS | C35: 25 | D35: Male | E35: Tristanton | F35: Oklahoma | G35: USA | H35: Platinum
A36: CUST1034 | B36: Christopher Olson | C36: 27 | D36: Female | E36: West Richard | F36: Maryland | G36: USA | H36: Platinum
A37: CUST1035 | B37: Rachel Myers | C37: 52 | D37: Male | E37: Robertberg | F37: North Dakota | G37: USA | H37: Silver
A38: CUST1036 | B38: Thomas Phillips | C38: 20 | D38: Female | E38: Luisfurt | F38: Georgia | G38: USA | H38: Gold
A39: CUST1037 | B39: Christopher Carter | C39: 27 | D39: Female | E39: Brendastad | F39: South Dakota | G39: USA
A40: CUST1038 | B40: Deanna Simpson | C40: 35 | D40: Female | E40: Brownport | F40: North Dakota | G40: USA | H40: Bronze
A41: CUST1039 | B41: Tonya Reynolds | C41: 55 | D41: Female | E41: Darleneton | F41: Michigan | G41: USA | H41: Gold
A42: CUST1040 | B42: Eric Vega | C42: 50 | D42: Male | E42: Williamsonland | F42: Kansas | G42: USA | H42: Gold
A43: CUST1041 | B43: James Gibbs | C43: 21 | D43: Male | E43: Mooneyshire | F43: Alaska | G43: USA | H43: Platinum
A44: CUST1042 | B44: William Martin | C44: 19 | D44: Male | E44: Ryanburgh | F44: Connecticut | G44: USA | H44: Platinum
A45: CUST1043 | B45: Joseph Snow | C45: 45 | D45: Male | E45: South Michaelfort | F45: Vermont | G45: USA | H45: Gold
A46: CUST1044 | B46: Denise Williams | C46: 34 | D46: Male | E46: Christianstad | F46: Hawaii | G46: USA | H46: Bronze
A47: CUST1045 | B47: Jordan Jackson DDS | C47: 54 | D47: Male | E47: North Johnview | F47: Arizona | G47: USA | H47: Gold
A48: CUST1046 | B48: Michelle Garcia DDS | C48: 55 | D48: Female | E48: Perezbury | F48: Ohio | G48: USA | H48: Platinum
A49: CUST1047 | B49: Gina Knight | C49: 54 | D49: Female | E49: Lake Roberthaven | F49: Nevada | G49: USA | H49: Silver
A50: CUST1048 | B50: April Mullins | C50: 54 | D50: Male | E50: Dawsonbury | F50: North Carolina | G50: USA | H50: Platinum
A51: CUST1049 | B51: Timothy Weaver | C51: 45 | D51: Female | E51: New Amy | F51: Ohio | G51: USA | H51: Gold
... A501: C-1499 | B501: Philip Pennington | C501: 27 | D501: Female | E501: East Valerieview | F501: Oregon | G501: USA | H501: Platinum

Sheet Cleaned Customer_Dim
A1: Customer_ID | B1: Name | C1: Age | D1: Gender | E1: City | F1: State | G1: Country | H1: Loyalty_Level.1
A2: CUST1000 | B2: Sheena Bonilla | C2: 55 | D2: Male | E2: Donaldton | F2: North Carolina | G2: USA | H2: Unknown
A3: CUST1001 | B3: Eugene Nelson | C3: 26 | D3: Female | E3: Phillipsmouth | F3: North Dakota | G3: USA | H3: Platinum
A4: CUST1002 | B4: Dr. Benjamin Price | C4: 29 | D4: Female | E4: Kylebury | F4: Alabama | G4: USA | H4: Platinum
A5: CUST1003 | B5: Jeremy Harris | C5: 59 | D5: Female | E5: Thomastown | F5: Ohio | G5: USA | H5: Bronze
A6: CUST1004 | B6: Caroline Collins | C6: 64 | D6: Female | E6: Nicholasshire | F6: California | G6: USA | H6: Silver
A7: CUST1005 | B7: Christine Vaughn | C7: 24 | D7: Male | E7: East Amandamouth | F7: Oregon | G7: USA | H7: Bronze
A8: CUST1006 | B8: Amber Jackson | C8: 29 | D8: Female | E8: Deborahborough | F8: South Dakota | G8: USA | H8: Platinum
A9: CUST1007 | B9: Daniel Boyd | C9: 29 | D9: Female | E9: West Pamelafurt | F9: West Virginia | G9: USA | H9: Bronze
A10: CUST1008 | B10: Melissa Howard | C10: 53 | D10: Female | E10: Maynardton | F10: New Hampshire | G10: USA | H10: Gold
A11: CUST1009 | B11: Ms. Maria Leach | C11: 64 | D11: Male | E11: Melissashire | F11: Pennsylvania | G11: USA | H11: Platinum
A12: CUST1010 | B12: Dominic Page | C12: 53 | D12: Male | E12: Port Michaelburgh | F12: Pennsylvania | G12: USA | H12: Bronze
A13: CUST1011 | B13: Brian Lopez | C13: 28 | D13: Female | E13: East Krista | F13: New York | G13: USA | H13: Gold
... A501: CUST1499 | B501: Philip Pennington | C501: 27 | D501: Female | E501: East Valerieview | F501: Oregon | G501: USA | H501: Platinum

Sheet Product_Dim
A1: Product_ID | B1: Product_Name | C1: Category | D1: Sub_Category | E1: Brand | F1: Cost | G1: Stock
A2: PROD0 | B2: Brother Laser Printer | C2: Electronics | D2: Computer | E2: Hunt Inc | F2: 112.42 | G2: 416
A3: PROD1 | B3: Men's Graphic T-Shirt | C3: Clothing | D3: Tops | E3: Terry-Moore | F3: 342.56 | G3: 181
A4: PROD2 | B4: Women's Casual Hoodie | C4: Clothing | D4: Outerwear | E4: Sims Inc | G4: 352
A5: P-3 | B5: Men's Running Jacket | C5: Clothing | D5: Outerwear | E5: Pineda Ltd | F5: 364.67 | G5: 452
A6: PROD4 | B6: Women's Yoga Pants | C6: Clothing | D6: Bottoms | E6: Gonzales-Davis | F6: 306.46 | G6: 487
A7: PROD5 | B7: Men's Leather Belt | C7: Clothing | D7: Accessories | E7: Baldwin, Garza and Gonzalez | F7: 261 | G7: 59
A8: PROD6 | B8: Herbal Face Moisturizer | C8: Beauty | D8: Skincare | E8: Davidson PLC | F8: 312.8 | G8: 350
A9: PROD7 | B9: LED Table Lamp | C9: Home | D9: Lighting | E9: Harrell LLC | F9: 218.86 | G9: 170
A10: PROD8 | B10: Wireless Bluetooth Earbuds | C10: Electronics | D10: Audio | E10: Perez-Johnston | F10: 439.07 | G10: 142
A11: PROD9 | B11: Adjustable Dumbbell Set | C11: Sports | D11: Fitness | E11: Hill PLC | F11: 495.72 | G11: 323
A12: PROD10 | B12: Ceramic Kitchen Bowl Set | C12: Home | D12: Kitchen | E12: Hamilton Group | F12: 298.86 | G12: 308
A13: PROD11 | B13: HD Smart TV Stick | C13: Electronics | D13: Accessories | E13: Gibson, Hobbs and Weaver | F13: 449.4
A14: PROD12 | B14: Hair Strengthening Shampoo | C14: Beauty | D14: Haircare | E14: Rice LLC | F14: 115.82 | G14: 460
A15: PROD13 | B15: USB-C Fast Charger | C15: Electronics | D15: Accessories | E15: Dawson-Perkins | F15: 242.23 | G15: 453
A16: PROD14 | B16: Decorative Wall Mirror | C16: Home | D16: Decor | E16: Luna, Anderson and Bowman | F16: 48.01 | G16: 439
A17: PROD15 | B17: 4K Home Projector | C17: Electronics | D17: Appliances | E17: Thomas LLC | F17: 465.34 | G17: 301
A18: P-16 | B18: Beard Grooming Kit | C18: Beauty | D18: Grooming | E18: Erickson-Green | F18: 337.42 | G18: 256
A19: PROD17 | B19: Soccer Training Cone Set | C19: Sports | D19: Accessories | E19: Ford, Murphy and Wilson | F19: 144.53 | G19: 367
A20: PROD18 | B20: Women's Denim Jeans | C20: Clothing | D20: Bottoms | E20: Guerra-Hendrix | G20: 343
A21: PROD19 | B21: Knee Support Brace | C21: Sports | D21: Equipment | E21: May-Reese | F21: 21.34 | G21: 65
A22: PROD20 | B22: Outdoor Sports Water Bottle | C22: Sports | D22: Accessories | E22: Soto-Ellis | F22: 131.51
A23: PROD21 | B23: Multi-Purpose Storage Box | C23: Home | D23: Storage | E23: Gardner-Montes | F23: 123.46 | G23: 76
A24: PROD22 | B24: Carbon Fiber Tennis Racket | C24: Sports | D24: Equipment | E24: Flores, Pineda and Rodriguez | F24: 484.62 | G24: 432
A25: PROD23 | B25: Men's Formal Shirt | C25: Clothing | D25: Tops | E25: Moon, Mora and Santos | G25: 360
A26: PROD24 | B26: Foldable Camping Chair | C26: Sports | D26: Outdoor | E26: Cook Ltd | F26: 166.06 | G26: 340
A27: PROD25 | B27: Women's Scarf Set | C27: Clothing | D27: Accessories | E27: Brown and Sons | F27: 174.02 | G27: 268
A28: PROD26 | B28: Wireless Bluetooth Speaker | C28: Electronics | D28: Audio | E28: Reed-Schmidt | F28: 322.41 | G28: 213
A29: PROD27 | B29: Decorative Floor Vase | C29: Home | D29: Decor | E29: Khan, Jones and Paul | G29: 378
A30: PROD28 | B30: Sports Stopwatch Timer | C30: Sports | D30: Accessories | E30: Burns-Hansen | F30: 38.76 | G30: 137
A31: PROD29 | B31: Fabric Sofa Throw Blanket | C31: Home | D31: Decor | E31: Hoffman Group | F31: 218.48 | G31: 276
A32: PROD30 | B32: Stainless Steel Cutlery Set | C32: Home | D32: Kitchen | E32: Stevens, Fernandez and Martin | F32: 19.52 | G32: 57
A33: PROD31 | B33: Basketball | C33: Sports | D33: Team Sports | E33: Nolan-Snow | F33: 204.39 | G33: 281
A34: PROD32 | B34: Vitamin C Face Serum | C34: Beauty | D34: Skincare | E34: Griffin Ltd | F34: 283.83 | G34: 244
A35: PROD33 | B35: Modern Wall Clock | C35: Home | D35: Decor | E35: Weiss-Watson | F35: 179.77 | G35: 305
A36: PROD34 | B36: Gaming Mechanical Keyboard | C36: Electronics | D36: Computer | E36: Lucero LLC | F36: 419.28 | G36: 86
A37: PROD35 | B37: Bedroom Table Lamp | C37: Home | D37: Lighting | E37: Jones LLC | F37: 382.22 | G37: 329
A38: PROD36 | B38: Women's Summer Dress | C38: Clothing | D38: Tops | E38: Smith-Mills | F38: 223.43 | G38: 154
A39: PROD37 | B39: Men's Casual Sneakers | C39: Clothing | D39: Footwear | E39: Hogan-Lee | F39: 353.47 | G39: 214
A40: PROD38 | B40: Sports Water Hydration Pack | C40: Sports | D40: Outdoor | E40: Sims-Smith | F40: 135.61 | G40: 394
A41: PROD39 | B41: Portable Power Bank | C41: Electronics | D41: Mobile | E41: Cummings and Sons | F41: 326.06 | G41: 301
... A48: PROD46 | B48: Men's Winter Jacket | C48: Clothing | D48: Outerwear | E48: Kelly, Smith and Perez | F48: 167.34 | G48: 296
A49: PROD47 | B49: Makeup Brush Set | C49: Beauty | D49: Makeup | E49: Cook Inc | G49: 431
A50: PROD48 | B50: Car Dashboard Phone Holder | C50: Electronics | D50: Accessories | E50: Byrd, Stewart and Valdez | F50: 177.98 | G50: 103
A51: PROD49 | B51: Men's Roll-On Perfume | C51: Beauty | D51: Fragrance | E51: Sullivan and Sons | F51: 43.29 | G51: 267
A52: PROD50 | B52: Boxing Hand Wraps | C52: Sports | D52: Fitness | E52: Smith-King | F52: 190.29 | G52: 260
A53: PROD51 | B53: HDMI Cable – 2m | C53: Electronics | D53: Accessories | E53: Bautista, Green and Hale | F53: 88.49 | G53: 246
A54: PROD52 | B54: Rugby Ball | C54: Sports | D54: Team Sports | E54: Harris Inc | F54: 212.26 | G54: 82
A55: PROD53 | B55: Men's Track Pants | C55: Clothing | D55: Bottoms | E55: Hamilton, Woods and Walker | F55: 386.56 | G55: 125
A56: PROD54 | B56: Sports Stopwatch Pro | C56: Sports | D56: Accessories | E56: Thompson-French | F56: 434.84 | G56: 185
A57: PROD55 | B57: Ceramic Plant Pot | C57: Home | D57: Decor | E57: Hatfield, Baird and Torres | F57: 81.75
A58: PROD56 | B58: Premium Blanket Throw | C58: Home | D58: Decor | E58: Hernandez, Kennedy and Porter | F58: 461.47 | G58: 190
A59: PROD57 | B59: Foam Roller | C59: Sports | D59: Fitness | E59: Atkinson, Camacho and Oliver | F59: 30.62 | G59: 138
A60: PROD58 | B60: Womens Cotton Scarf | C60: Clothing | D60: Accessories | E60: Shepherd-Gould | F60: 113.83 | G60: 485
A61: PROD59 | B61: Men's Hair Styling Gel | C61: Beauty | D61: Haircare | E61: Cline-Mccarthy | F61: 17.31 | G61: 399
A62: PROD60 | B62: Luxury Perfume Spray | C62: Beauty | D62: Fragrance | E62: Gibson, Green and Lopez | F62: 482.75 | G62: 444
A63: PROD61 | B63: Tennis Ball 3-Pack | C63: Sports | D63: Equipment | E63: Lopez LLC | F63: 103.45 | G63: 465
A64: PROD62 | B64: Laptop Cooling Pad | C64: Electronics | D64: Computer | E64: Murray, Gould and Ware | F64: 86.42 | G64: 222
A65: PROD63 | B65: Organic Sunscreen Lotion | C65: Beauty | D65: Skincare | E65: Anderson-Riley | F65: 266.86 | G65: 458
A66: PROD64 | B66: Matte Lipstick Set | C66: Beauty | D66: Makeup | E66: Zhang Inc | F66: 299.11 | G66: 118
A67: PROD65 | B67: Adjustable Dumbbells 20kg | C67: Sports | D67: Fitness | E67: Montgomery, Benton and Miller | F67: 240.63 | G67: 423
A68: PROD66 | B68: Women's Hair Dryer Brush | C68: Beauty | D68: Haircare | E68: Torres, Spencer and Potter | F68: 340.39 | G68: 177
A69: PROD67 | B69: Smart LED Light Strip | C69: Electronics | D69: Accessories | E69: Flores-Davis | F69: 349.17 | G69: 476
... A84: PROD82 | B84: Fitness Resistance Bands | C84: Sports | D84: Fitness | E84: Reese-Watson | F84: 152.92 | G84: 281
A85: PROD83 | B85: Hydrating Face Cleanser | C85: Beauty | D85: Skincare | E85: Butler Group | G85: 159
A86: PROD84 | B86: Wooden Bookshelf | C86: Home | D86: Furniture | E86: Collins-Stephenson | F86: 388.46 | G86: 208
A87: PROD85 | B87: Women's Beanie Hat | C87: Clothing | D87: Accessories | E87: Richardson-Carrillo | F87: 119.57 | G87: 210
A88: PROD86 | B88: Kitchen Cutting Board | C88: Home | D88: Kitchen | E88: Taylor, Dodson and Johnston | F88: 176.07 | G88: 82
A89: PROD87 | B89: LED Bedside Lamp | C89: Home | D89: Lighting | E89: Aguilar, Horton and Lewis | F89: 371.38 | G89: 220
A90: PROD88 | B90: Sports Wrist Sweatbands | C90: Sports | D90: Accessories | E90: Olsen-Daniels | F90: 131.24 | G90: 232
A91: PROD89 | B91: Face Foundation Kit | C91: Beauty | D91: Makeup | E91: Taylor-Elliott | F91: 183.04 | G91: 457
A92: PROD90 | B92: Gaming Mouse Pad XL | C92: Electronics | D92: Accessories | E92: Sharp, Taylor and Rodriguez | F92: 340.14 | G92: 361
A93: PROD91 | B93: Women's High Heels | C93: Clothing | D93: Footwear | E93: Smith-Charles | F93: 438.25 | G93: 496
A94: PROD92 | B94: Microwave Oven | C94: Home | D94: Appliances | E94: Green, Powell and Palmer | F94: 447.43 | G94: 191
A95: PROD93 | B95: USB-C Laptop Charger | C95: Electronics | D95: Computer | E95: Martin LLC | F95: 377.52 | G95: 485
A96: PROD94 | B96: Vitamin E Body Lotion | C96: Beauty | D96: Skincare | E96: Hoffman-Williams | F96: 358.47 | G96: 213
A97: PROD95 | B97: Sports Stopwatch Basic | C97: Sports | D97: Accessories | E97: Wilson Group | F97: 60.65 | G97: 75
... A101: PROD99 | B101: Stainless Steel Cookware Set | C101: Home | D101: Kitchen | E101: Campbell Ltd | F101: 201.41 | G101: 146

Sheet Cleaned Product Dim Dataset
A1: Product_ID | B1: Product_Name | C1: Category | D1: Sub_Category | E1: Brand | F1: Cost | G1: Stock
A2: PROD0 | B2: Brother Laser Printer | C2: Electronics | D2: Computer | E2: Hunt Inc | F2: 113 | G2: 416
A3: PROD1 | B3: Men's Graphic T-Shirt | C3: Clothing | D3: Tops | E3: Terry-Moore | F3: 343 | G3: 181
A4: PROD2 | B4: Women's Casual Hoodie | C4: Clothing | D4: Outerwear | E4: Sims Inc | F4: 255 | G4: 352
A5: PROD3 | B5: Men's Running Jacket | C5: Clothing | D5: Outerwear | E5: Pineda Ltd | F5: 365 | G5: 452
A6: PROD4 | B6: Women's Yoga Pants | C6: Clothing | D6: Bottoms | E6: Gonzales-Davis | F6: 307 | G6: 487
A7: PROD5 | B7: Men's Leather Belt | C7: Clothing | D7: Accessories | E7: Baldwin, Garza and Gonzalez | F7: 261 | G7: 59
A8: PROD6 | B8: Herbal Face Moisturizer | C8: Beauty | D8: Skincare | E8: Davidson PLC | F8: 313 | G8: 350
A9: PROD7 | B9: LED Table Lamp | C9: Home | D9: Lighting | E9: Harrell LLC | F9: 219 | G9: 170
A10: PROD8 | B10: Wireless Bluetooth Earbuds | C10: Electronics | D10: Audio | E10: Perez-Johnston | F10: 440 | G10: 142
A11: PROD9 | B11: Adjustable Dumbbell Set | C11: Sports | D11: Fitness | E11: Hill PLC | F11: 496 | G11: 323
A12: PROD10 | B12: Ceramic Kitchen Bowl Set | C12: Home | D12: Kitchen | E12: Hamilton Group | F12: 299 | G12: 308
A13: PROD11 | B13: HD Smart TV Stick | C13: Electronics | D13: Accessories | E13: Gibson, Hobbs and Weaver | F13: 450 | G13: 274
... A101: PROD99 | B101: Stainless Steel Cookware Set | C101: Home | D101: Kitchen | E101: Campbell Ltd | F101: 202 | G101: 146

Sheet Store_Dim
A1: Store_ID | B1: Store_Name | C1: Region | D1: City | E1: Store_Type
A2: STORE0 | B2: Rivera-Warner | C2: East | D2: Washingtonfurt | E2: Flagship
A3: STORE1 | B3: Martinez, Adkins and Johnson | C3: North | D3: Danielmouth | E3: Flagship
A4: STORE2 | B4: Black-Horn | C4: South | D4: North Nancyview | E4: Outlet
A5: STORE3 | B5: Johnson-Wright | C5: North | D5: Hoodberg | E5: Outlet
A6: STORE4 | B6: Alexander Group | C6: South | D6: Port Sharon | E6: Online
A7: STORE5 | B7: Gray Ltd | C7: North | D7: New Michaelchester | E7: Outlet
A8: STORE6 | B8: Benson-Elliott | C8: East | D8: Port Josephberg | E8: Online
A9: STORE7 | B9: Martinez-Mullins | C9: South | D9: Williamsfurt | E9: Online
A10: STORE8 | B10: Bean, Jones and Park | C10: West | D10: Thompsonborough | E10: Online
A11: STORE9 | B11: Moore, Padilla and Butler | C11: South | D11: East Johnstad | E11: Flagship
A12: STORE10 | B12: Hill, Wagner and Ballard | C12: East | D12: East Davidville | E12: Online
... A21: STORE19 | B21: Mann-Austin | C21: East | D21: Vasquezborough | E21: Online

Sheet Cleaned Stoer_ Dim
A1: Store_ID | B1: Store_Name | C1: Region | D1: City | E1: Store_Type
A2: STORE0 | B2: Rivera-Warner | C2: East | D2: Washingtonfurt | E2: Flagship
A3: STORE1 | B3: Martinez, Adkins and Johnson | C3: North | D3: Danielmouth | E3: Flagship
A4: STORE2 | B4: Black-Horn | C4: South | D4: North Nancyview | E4: Outlet
A5: STORE3 | B5: Johnson-Wright | C5: North | D5: Hoodberg | E5: Outlet
A6: STORE4 | B6: Alexander Group | C6: South | D6: Port Sharon | E6: Online
A7: STORE5 | B7: Gray Ltd | C7: North | D7: New Michaelchester | E7: Outlet
A8: STORE6 | B8: Benson-Elliott | C8: East | D8: Port Josephberg | E8: Online
A9: STORE7 | B9: Martinez-Mullins | C9: South | D9: Williamsfurt | E9: Online
A10: STORE8 | B10: Bean, Jones and Park | C10: West | D10: Thompsonborough | E10: Online
A11: STORE9 | B11: Moore, Padilla and Butler | C11: South | D11: East Johnstad | E11: Flagship
A12: STORE10 | B12: Hill, Wagner and Ballard | C12: East | D12: East Davidville | E12: Online
... A21: STORE19 | B21: Mann-Austin | C21: East | D21: Vasquezborough | E21: Online

Sheet Sales_Fact
A1: Sales_ID | B1: Order_Date | C1: Customer_ID | D1: Product_ID | E1: Store_ID | F1: Quantity | G1: Unit_Price | H1: Discount | I1: Payment_Type | J1: Total_Amount
A2: SALE0 | B2: 45480 | C2: CUST1409 | D2: PROD97 | E2: STORE3 | F2: 1 | G2: 218.04 | H2: 0.09 | I2: Credit Card | J2: 198.4164
A3: SALE1 | B3: 45285 | C3: CUST1467 | D3: PROD74 | E3: STORE17 | F3: 3 | G3: 104.47 | H3: 0.27 | I3: PayPal | J3: 228.7893
A4: SALE2 | B4: 45446 | C4: CUST1056 | D4: PROD49 | E4: STORE8 | F4: 4 | G4: 914.05 | H4: 0.25 | I4: Credit Card | J4: 2742.15
A5: SALE3 | B5: 45259 | C5: CUST1346 | D5: PROD76 | E5: STORE8 | F5: 1 | G5: 921.51 | H5: 0.16 | I5: COD | J5: 774.0684
A6: SALE4 | B6: 45297 | C6: CUST1493 | D6: PROD59 | E6: STORE5 | F6: 3 | G6: 745.3 | H6: 0.18 | I6: Credit Card | J6: 1833.438
A7: SALE5 | B7: 45499 | C7: CUST1116 | D7: PROD15 | E7: STORE7 | F7: 3 | G7: 147.01 | H7: 0.19 | I7: COD | J7: 357.2343
A8: SALE6 | B8: 45850 | C8: CUST1016 | D8: PROD56 | E8: STORE4 | F8: 2 | G8: 785.31 | H8: 0.15 | I8: PayPal | J8: 1335.027
A9: SALE7 | B9: 45248 | C9: CUST1152 | D9: PROD70 | E9: STORE8 | F9: 4 | G9: 342.39 | H9: 0.23 | I9: PayPal | J9: 1054.5612
A10: SALE8 | B10: 45781 | C10: CUST1187 | D10: PROD99 | E10: STORE5 | G10: 448.25 | H10: 0.07 | I10: PayPal | J10: 1250.6175
A11: SALE9 | B11: 45869 | C11: CUST1464 | D11: PROD33 | E11: STORE0 | F11: 2 | G11: 873.17 | H11: 0.23 | I11: PayPal | J11: 1344.6818
A12: SALE10 | B12: 45335 | C12: CUST1065 | D12: PROD24 | E12: STORE14 | F12: 1 | G12: 278.63 | H12: 0.07 | I12: Credit Card | J12: 259.1259
A13: SALE11 | B13: 45801 | C13: CUST1320 | D13: PROD39 | E13: STORE1 | F13: 4 | G13: 286.92 | H13: 0.17 | I13: Credit Card | J13: 952.5744
A14: SALE12 | B14: 45528 | C14: CUST1237 | D14: PROD88 | E14: STORE4 | F14: 4 | G14: 644.58 | H14: 0.01 | I14: Credit Card | J14: 2552.5368
A15: SALE13 | B15: 45875 | C15: CUST1443 | D15: PROD34 | E15: STORE16 | F15: 2 | G15: 316.9 | H15: 0.3 | I15: PayPal | J15: 443.66
A16: SALE14 | B16: 45829 | C16: CUST1348 | D16: PROD24 | E16: STORE15 | F16: 4 | G16: 403.47 | H16: 0.29 | I16: PayPal | J16: 1145.8548
A17: SALE15 | B17: 45636 | C17: CUST1435 | D17: PROD36 | E17: STORE9 | G17: 871.34 | H17: 0.04 | I17: COD | J17: 2509.4592
A18: SALE16 | B18: 45913 | C18: CUST1276 | D18: PROD65 | E18: STORE19 | F18: 2 | G18: 451.98 | H18: 0.25 | I18: Credit Card | J18: 677.97
A19: SALE17 | B19: 45637 | C19: CUST1079 | D19: PROD27 | E19: STORE4 | F19: 2 | G19: 502.69 | H19: 0.23 | I19: Credit Card | J19: 774.1426
A20: SALE18 | B20: 45517 | C20: CUST1094 | D20: PROD39 | E20: STORE4 | F20: 2 | G20: 559.23 | H20: 0.25 | I20: COD | J20: 838.845
A21: SALE19 | B21: 45369 | C21: CUST1239 | D21: PROD60 | E21: STORE13 | F21: 4 | H21: 0.04 | I21: COD | J21: 1782.4512
A22: SALE20 | B22: 45843 | C22: CUST1144 | D22: PROD72 | E22: STORE17 | F22: 3 | G22: 986.04 | H22: 0.27 | I22: COD | J22: 2159.4276
A23: SALE21 | B23: 45447 | C23: CUST1396 | D23: PROD43 | E23: STORE18 | F23: 1 | G23: 589.56 | H23: 0.22 | I23: Credit Card | J23: 459.8568
A24: SALE22 | B24: 45394 | C24: CUST1476 | D24: PROD69 | E24: STORE10 | F24: 3 | G24: 979.42 | H24: 0.03 | I24: PayPal | J24: 2850.1122
A25: SALE23 | B25: 45466 | C25: CUST1368 | D25: PROD12 | E25: STORE8 | F25: 1 | G25: 719.28 | H25: 0.08 | I25: Credit Card | J25: 661.7376
A26: SALE24 | B26: 45908 | C26: CUST1186 | D26: PROD67 | E26: STORE6 | F26: 3 | G26: 77.6 | H26: 0.07 | I26: Credit Card | J26: 216.504
A27: SALE25 | B27: 45552 | C27: CUST1381 | D27: PROD5 | E27: STORE3 | F27: 4 | G27: 852.71 | H27: 0.14 | I27: PayPal | J27: 2933.3224
A28: SALE26 | B28: 45294 | C28: CUST1213 | D28: PROD98 | E28: STORE8 | F28: 4 | G28: 156.16 | I28: Credit Card | J28: 599.6544
A29: SALE27 | B29: 45710 | C29: CUST1200 | D29: PROD77 | E29: STORE8 | F29: 3 | G29: 815.49 | H29: 0.17 | I29: Credit Card | J29: 2030.5701
A30: SALE28 | B30: 45923 | C30: CUST1148 | D30: PROD13 | E30: STORE2 | F30: 2 | G30: 74.21 | H30: 0.11 | I30: PayPal | J30: 132.0938
A31: SALE29 | B31: 45302 | C31: CUST1348 | D31: PROD99 | E31: STORE3 | G31: 451.67 | H31: 0.15 | I31: Credit Card | J31: 1535.678
A32: SALE30 | B32: 45217 | C32: CUST1028 | D32: PROD5 | E32: STORE19 | F32: 1 | G32: 429.38 | H32: 0.13 | I32: PayPal | J32: 373.5606
A33: SALE31 | B33: 45593 | C33: CUST1412 | D33: PROD53 | E33: STORE12 | F33: 2 | G33: 148.96 | H33: 0.03 | I33: COD | J33: 288.9824
A34: SALE32 | B34: 45597 | C34: CUST1398 | D34: PROD75 | E34: STORE8 | F34: 4 | G34: 313.83 | H34: 0.08 | I34: Credit Card | J34: 1154.8944
A35: SALE33 | B35: 45620 | C35: CUST1453 | D35: PROD12 | E35: STORE6 | F35: 2 | G35: 717.31 | H35: 0.15 | I35: Credit Card | J35: 1219.427
A36: SALE34 | B36: 45215 | C36: CUST1344 | D36: PROD79 | E36: STORE1 | G36: 873.22 | H36: 0.18 | I36: Credit Card | J36: 2148.1212
A37: SALE35 | B37: 45878 | C37: CUST1218 | D37: PROD16 | E37: STORE3 | F37: 4 | G37: 109.36 | H37: 0.19 | I37: COD | J37: 354.3264
A38: SALE36 | B38: 45635 | C38: CUST1086 | D38: PROD5 | E38: STORE7 | F38: 3 | G38: 559.52 | H38: 0.16 | I38: PayPal | J38: 1409.9904
A39: SALE37 | B39: 45329 | C39: CUST1492 | D39: PROD10 | E39: STORE17 | F39: 3 | G39: 121.76 | H39: 0.27 | I39: PayPal | J39: 266.6544
A40: SALE38 | B40: 45378 | C40: CUST1189 | D40: PROD33 | E40: STORE13 | F40: 4 | G40: 735.32 | H40: 0.06 | I40: COD | J40: 2764.8032
A41: SALE39 | B41: 45264 | C41: CUST1431 | D41: PROD94 | E41: STORE3 | F41: 2 | G41: 600.73 | H41: 0.08 | I41: Credit Card | J41: 1105.3432
A42: SALE40 | B42: 45486 | C42: CUST1072 | D42: PROD26 | E42: STORE19 | F42: 2 | G42: 873.86 | H42: 0.07 | I42: COD | J42: 1625.3796
A43: SALE41 | B43: 45241 | C43: CUST1302 | D43: PROD23 | E43: STORE8 | F43: 3 | G43: 342.47 | H43: 0.08 | I43: PayPal | J43: 945.2172
A44: SALE42 | B44: 45649 | C44: CUST1335 | D44: PROD29 | E44: STORE9 | F44: 2 | G44: 915.15 | H44: 0.16 | I44: PayPal | J44: 1537.452
A45: SALE43 | B45: 45677 | C45: CUST1084 | D45: PROD33 | E45: STORE17 | G45: 863.11 | H45: 0.28 | I45: PayPal | J45: 1864.3176
A46: SALE44 | B46: 45538 | C46: CUST1203 | D46: PROD43 | E46: STORE12 | F46: 2 | G46: 209.32 | H46: 0.23 | I46: COD | J46: 322.3528
A47: SALE45 | B47: 45606 | C47: CUST1470 | D47: PROD59 | E47: STORE8 | F47: 4 | G47: 288.6 | H47: 0.09 | I47: PayPal | J47: 1050.504
A48: SALE46 | B48: 45570 | C48: CUST1070 | D48: PROD78 | E48: STORE16 | F48: 1 | G48: 418.69 | H48: 0.06 | I48: PayPal | J48: 393.5686
A49: SALE47 | B49: 45466 | C49: CUST1008 | D49: PROD30 | E49: STORE11 | F49: 1 | G49: 135.78 | H49: 0.14 | I49: PayPal | J49: 116.7708
A50: SALE48 | B50: 45218 | C50: CUST1203 | D50: PROD44 | E50: STORE17 | F50: 1 | G50: 517.13 | H50: 0.28 | I50: Credit Card | J50: 372.3336
A51: SALE49 | B51: 45607 | C51: CUST1420 | D51: PROD21 | E51: STORE16 | F51: 2 | G51: 384.66 | H51: 0.08 | I51: COD | J51: 707.7744
A52: SALE50 | B52: 45291 | C52: CUST1070 | D52: PROD52 | E52: STORE9 | F52: 3 | G52: 83.7 | H52: 0.24 | I52: PayPal | J52: 190.836
A53: SALE51 | B53: 45689 | C53: CUST1142 | D53: PROD69 | E53: STORE7 | F53: 3 | G53: 76.57 | H53: 0.26 | I53: Credit Card | J53: 169.9854
A54: SALE52 | B54: 45894 | C54: CUST1148 | D54: PROD89 | E54: STORE6 | F54: 3 | I54: Credit Card | J54: 486.0633
A55: SALE53 | B55: 45677 | C55: CUST1324 | D55: PROD20 | E55: STORE8 | F55: 1 | G55: 900.35 | H55: 0.13 | I55: COD | J55: 783.3045
A56: SALE54 | B56: 45706 | C56: CUST1095 | D56: PROD40 | E56: STORE10 | F56: 4 | G56: 428.09 | H56: 0.07 | I56: Credit Card | J56: 1592.4948
A57: SALE55 | B57: 45589 | C57: CUST1416 | D57: PROD49 | E57: STORE11 | F57: 2 | G57: 559.71 | H57: 0.3 | I57: COD | J57: 783.594
A58: SALE56 | B58: 45282 | C58: CUST1080 | D58: PROD34 | E58: STORE6 | F58: 2 | G58: 833.7 | H58: 0.06 | I58: PayPal | J58: 1567.356
A59: SALE57 | B59: 45462 | C59: CUST1467 | D59: PROD47 | E59: STORE14 | F59: 2 | G59: 680.16 | H59: 0.28 | I59: Credit Card | J59: 979.4304
A60: SALE58 | B60: 45633 | C60: CUST1404 | D60: PROD15 | E60: STORE7 | F60: 4 | G60: 733.42 | I60: PayPal | J60: 2552.3016
A61: SALE59 | B61: 45257 | C61: CUST1367 | D61: PROD89 | E61: STORE11 | F61: 1 | G61: 996.33 | H61: 0.23 | I61: PayPal | J61: 767.1741
A62: SALE60 | B62: 45854 | C62: CUST1408 | D62: PROD31 | E62: STORE10 | F62: 1 | G62: 198.83 | H62: 0.09 | I62: COD | J62: 180.9353
A63: SALE61 | B63: 45716 | C63: CUST1239 | D63: PROD19 | E63: STORE7 | F63: 1 | G63: 374.92 | H63: 0.18 | I63: PayPal | J63: 307.4344
A64: SALE62 | B64: 45515 | C64: CUST1464 | D64: PROD93 | E64: STORE16 | F64: 1 | G64: 468.94 | H64: 0.12 | I64: Credit Card | J64: 412.6672
A65: SALE63 | B65: 45927 | C65: CUST1126 | D65: PROD89 | E65: STORE12 | F65: 2 | G65: 121.37 | H65: 0.05 | I65: Credit Card | J65: 230.603
A66: SALE64 | B66: 45914 | C66: CUST1255 | D66: PROD53 | E66: STORE10 | F66: 3 | G66: 480.06 | H66: 0.01 | I66: Credit Card
A67: SALE65 | B67: 45290 | C67: CUST1162 | D67: PROD99 | E67: STORE17 | F67: 2 | G67: 856.57 | H67: 0.24 | I67: Credit Card | J67: 1301.9864
A68: SALE66 | B68: 45213 | C68: CUST1269 | D68: PROD77 | E68: STORE2 | F68: 4 | G68: 814.25 | H68: 0.18 | I68: Credit Card | J68: 2670.74
A69: SALE67 | B69: 45255 | C69: CUST1483 | D69: PROD12 | E69: STORE2 | F69: 1 | G69: 989.17 | H69: 0.2 | I69: PayPal | J69: 791.336
A70: SALE68 | B70: 45270 | C70: CUST1372 | D70: PROD72 | E70: STORE10 | F70: 4 | G70: 62.48 | H70: 0.18 | I70: Credit Card | J70: 204.9344
A71: SALE69 | B71: 45897 | C71: CUST1423 | D71: PROD13 | E71: STORE16 | F71: 4 | G71: 561.24 | H71: 0.24 | I71: Credit Card | J71: 1706.1696
A72: SALE70 | B72: 45849 | C72: CUST1058 | D72: PROD60 | E72: STORE5 | F72: 3 | G72: 92.24 | H72: 0.28 | I72: COD
A73: SALE71 | B73: 45889 | C73: CUST1168 | D73: PROD72 | E73: STORE1 | F73: 2 | G73: 668.3 | H73: 0.07 | I73: Credit Card | J73: 1243.038
A74: SALE72 | B74: 45533 | C74: CUST1409 | D74: PROD38 | E74: STORE5 | F74: 1 | G74: 553.82 | H74: 0.09 | I74: Credit Card | J74: 503.9762
A75: SALE73 | B75: 45626 | C75: CUST1037 | D75: PROD45 | E75: STORE11 | F75: 2 | G75: 556.43 | H75: 0.13 | I75: Credit Card | J75: 968.1882
A76: SALE74 | B76: 45942 | C76: CUST1273 | D76: PROD20 | E76: STORE8 | F76: 1 | G76: 184.98 | H76: 0.1 | I76: COD | J76: 166.482
A77: SALE75 | B77: 45500 | C77: CUST1035 | D77: PROD97 | E77: STORE12 | F77: 4 | G77: 700.18 | H77: 0.23 | I77: Credit Card | J77: 2156.5544
A78: SALE76 | B78: 45285 | C78: CUST1019 | D78: PROD76 | E78: STORE10 | F78: 2 | G78: 686.31 | H78: 0.25 | I78: Credit Card | J78: 1029.465
A79: SALE77 | B79: 45800 | C79: CUST1007 | D79: PROD67 | E79: STORE15 | F79: 1 | G79: 687.82 | H79: 0.27 | I79: COD | J79: 502.1086
A80: SALE78 | B80: 45609 | C80: CUST1221 | D80: PROD83 | E80: STORE8 | F80: 2 | G80: 900.55 | H80: 0.16 | I80: Credit Card | J80: 1512.924
A81: SALE79 | B81: 45268 | C81: CUST1115 | D81: PROD21 | E81: STORE2 | F81: 1 | G81: 341.17 | H81: 0.15 | I81: Credit Card | J81: 289.9945
A82: SALE80 | B82: 45885 | C82: CUST1176 | D82: PROD52 | E82: STORE8 | F82: 1 | G82: 442.27 | H82: 0.06 | I82: COD | J82: 415.7338
A83: SALE81 | B83: 45616 | C83: CUST1253 | D83: PROD71 | E83: STORE9 | F83: 1 | G83: 363.73 | H83: 0.25 | I83: PayPal | J83: 272.7975
A84: SALE82 | B84: 45518 | C84: CUST1378 | D84: PROD91 | E84: STORE17 | F84: 2 | G84: 601.33 | H84: 0.16 | I84: PayPal | J84: 1010.2344
A85: SALE83 | B85: 45427 | C85: CUST1403 | D85: PROD17 | E85: STORE18 | F85: 4 | G85: 34.39 | H85: 0.03 | I85: PayPal | J85: 133.4332
A86: SALE84 | B86: 45268 | C86: CUST1423 | D86: PROD46 | E86: STORE17 | F86: 1 | G86: 773.57 | H86: 0.05 | I86: COD
A87: SALE85 | B87: 45282 | C87: CUST1054 | D87: PROD88 | E87: STORE7 | F87: 4 | G87: 127.1 | H87: 0.24 | I87: COD | J87: 386.384
A88: SALE86 | B88: 45545 | C88: CUST1303 | D88: PROD20 | E88: STORE3 | F88: 3 | G88: 899.58 | H88: 0.28 | I88: PayPal | J88: 1943.0928
A89: SALE87 | B89: 45755 | C89: CUST1327 | D89: PROD1 | E89: STORE10 | F89: 3 | G89: 964.39 | H89: 0.04 | I89: Credit Card | J89: 2777.4432
A90: SALE88 | B90: 45588 | C90: CUST1183 | D90: PROD38 | E90: STORE0 | F90: 2 | G90: 217.83 | H90: 0.14 | I90: PayPal | J90: 374.6676
A91: SALE89 | B91: 45848 | C91: CUST1143 | D91: PROD17 | E91: STORE1 | F91: 4 | G91: 187.71 | H91: 0.06 | I91: COD | J91: 705.7896
A92: SALE90 | B92: 45577 | C92: CUST1010 | D92: PROD33 | E92: STORE18 | F92: 2 | G92: 350.12 | H92: 0.12 | I92: COD | J92: 616.2112
A93: SALE91 | B93: 45312 | C93: CUST1406 | D93: PROD16 | E93: STORE1 | F93: 4 | G93: 102.19 | H93: 0.17 | I93: PayPal | J93: 339.2708
A94: SALE92 | B94: 45350 | C94: CUST1007 | D94: PROD86 | E94: STORE4 | F94: 1 | G94: 696.53 | H94: 0.17 | I94: Credit Card | J94: 578.1199
A95: SALE93 | B95: 45657 | C95: CUST1065 | D95: PROD19 | E95: STORE4 | F95: 2 | G95: 327.52 | H95: 0.15 | I95: PayPal | J95: 556.784
A96: SALE94 | B96: 45530 | C96: CUST1298 | D96: PROD97 | E96: STORE19 | F96: 2 | G96: 569.36 | H96: 0.01 | I96: PayPal
A97: SALE95 | B97: 45556 | C97: CUST1321 | D97: PROD99 | E97: STORE6 | F97: 2 | G97: 68.29 | H97: 0.14 | I97: COD | J97: 117.4588
A98: SALE96 | B98: 45523 | C98: CUST1244 | D98: PROD50 | E98: STORE10 | F98: 1 | G98: 842.9 | H98: 0.06 | I98: COD | J98: 792.326
A99: SALE97 | B99: 45587 | C99: CUST1287 | D99: PROD3 | E99: STORE3 | F99: 3 | G99: 751.94 | H99: 0.26 | I99: PayPal | J99: 1669.3068
A100: SALE98 | B100: 45580 | C100: CUST1131 | D100: PROD56 | E100: STORE7 | F100: 4 | G100: 476.28 | H100: 0.17 | I100: Credit Card | J100: 1581.2496
...

Sheet Cleaned Sales Fact 
A1: Sales_ID | B1: Order_Date | C1: Customer_ID | D1: Product_ID | E1: Store_ID | F1: Quantity | G1: Unit_Price | H1: Discount | I1: Payment_Type | J1: Total_Amount | K1: Gender | L1: Customer State | M1: Store name | N1: Store Region | O1: Store City | P1: Store type | Q1: Product Name | R1: Product Category | S1: Product Sub Category | T1: Product Brands
A2: SALE0 | B2: 45480 | C2: CUST1409 | D2: PROD97 | E2: STORE3 | F2: 1 | G2: 218.04 | H2: 0.09 | I2: Credit Card | J2: 198.42 | K2: =VLOOKUP(C2,'Cleaned Customer_Dim'!$A$2:$H$501,4,0) -> Male | L2: =VLOOKUP(C2, 'Cleaned Customer_Dim'!$A:$F, 6, FALSE) -> Wyoming | M2: =VLOOKUP(E2, 'Cleaned Stoer_ Dim'!$A$1:$E$21, 2, 0) -> Johnson-Wright | N2: =VLOOKUP(E2, 'Cleaned Stoer_ Dim'!$A:$E,3, 0) -> North | O2: =VLOOKUP(E2, 'Cleaned Stoer_ Dim'!$A:$E, 4, 0) -> Hoodberg | P2: =VLOOKUP(E2, 'Cleaned Stoer_ Dim'!$A:$E, 5, 0) -> Outlet | Q2: =VLOOKUP(D2, 'Cleaned Product Dim Dataset'!$A:$G, 2, 0) -> Cricket Bat | R2: =VLOOKUP(D2, 'Cleaned Product Dim Dataset'!$A:$G, 3, 0) -> Sports | S2: =VLOOKUP(D2, 'Cleaned Product Dim Dataset'!$A:$G, 4, 0) -> Team Sports | T2: =VLOOKUP(D2, 'Cleaned Product Dim Dataset'!$A:$G, 5, 0) -> Khan LLC
A3: SALE1 | B3: 45285 | C3: CUST1467 | D3: PROD74 | E3: STORE17 | F3: 3 | G3: 104.47 | H3: 0.27 | I3: PayPal | J3: 228.79 | K3: =VLOOKUP(C3,'Cleaned Customer_Dim'!$A$2:$H$501,4,0) -> Female | L3: =VLOOKUP(C3, 'Cleaned Customer_Dim'!$A:$F, 6, FALSE) -> Vermont | M3: =VLOOKUP(E3, 'Cleaned Stoer_ Dim'!$A$1:$E$21, 2, 0) -> Holloway Ltd | N3: =VLOOKUP(E3, 'Cleaned Stoer_ Dim'!$A:$E,3, 0) -> North | O3: =VLOOKUP(E3, 'Cleaned Stoer_ Dim'!$A:$E, 4, 0) -> Bensonhaven | P3: =VLOOKUP(E3, 'Cleaned Stoer_ Dim'!$A:$E, 5, 0) -> Flagship | Q3: =VLOOKUP(D3, 'Cleaned Product Dim Dataset'!$A:$G, 2, 0) -> Bluetooth Car Audio System | R3: =VLOOKUP(D3, 'Cleaned Product Dim Dataset'!$A:$G, 3, 0) -> Electronics | S3: =VLOOKUP(D3, 'Cleaned Product Dim Dataset'!$A:$G, 4, 0) -> Audio | T3: =VLOOKUP(D3, 'Cleaned Product Dim Dataset'!$A:$G, 5, 0) -> Bruce-Bowen
A4: SALE2 | B4: 45446 | C4: CUST1056 | D4: PROD49 | E4: STORE8 | F4: 4 | G4: 914.05 | H4: 0.25 | I4: Credit Card | J4: 2742.15 | K4: =VLOOKUP(C4,'Cleaned Customer_Dim'!$A$2:$H$501,4,0) -> Female | L4: =VLOOKUP(C4, 'Cleaned Customer_Dim'!$A:$F, 6, FALSE) -> Pennsylvania | M4: =VLOOKUP(E4, 'Cleaned Stoer_ Dim'!$A$1:$E$21, 2, 0) -> Bean, Jones and Park | N4: =VLOOKUP(E4, 'Cleaned Stoer_ Dim'!$A:$E,3, 0) -> West | O4: =VLOOKUP(E4, 'Cleaned Stoer_ Dim'!$A:$E, 4, 0) -> Thompsonborough | P4: =VLOOKUP(E4, 'Cleaned Stoer_ Dim'!$A:$E, 5, 0) -> Online | Q4: =VLOOKUP(D4, 'Cleaned Product Dim Dataset'!$A:$G, 2, 0) -> Men's Roll-On Perfume | R4: =VLOOKUP(D4, 'Cleaned Product Dim Dataset'!$A:$G, 3, 0) -> Beauty | S4: =VLOOKUP(D4, 'Cleaned Product Dim Dataset'!$A:$G, 4, 0) -> Fragrance | T4: =VLOOKUP(D4, 'Cleaned Product Dim Dataset'!$A:$G, 5, 0) -> Sullivan and Sons
A5: SALE3 | B5: 45259 | C5: CUST1346 | D5: PROD76 | E5: STORE8 | F5: 1 | G5: 921.51 | H5: 0.16 | I5: COD | J5: 774.07 | K5: =VLOOKUP(C5,'Cleaned Customer_Dim'!$A$2:$H$501,4,0) -> Female | L5: =VLOOKUP(C5, 'Cleaned Customer_Dim'!$A:$F, 6, FALSE) -> Tennessee | M5: =VLOOKUP(E5, 'Cleaned Stoer_ Dim'!$A$1:$E$21, 2, 0) -> Bean, Jones and Park | N5: =VLOOKUP(E5, 'Cleaned Stoer_ Dim'!$A:$E,3, 0) -> West | O5: =VLOOKUP(E5, 'Cleaned Stoer_ Dim'!$A:$E, 4, 0) -> Thompsonborough | P5: =VLOOKUP(E5, 'Cleaned Stoer_ Dim'!$A:$E, 5, 0) -> Online | Q5: =VLOOKUP(D5, 'Cleaned Product Dim Dataset'!$A:$G, 2, 0) -> Wireless Mouse | R5: =VLOOKUP(D5, 'Cleaned Product Dim Dataset'!$A:$G, 3, 0) -> Electronics | S5: =VLOOKUP(D5, 'Cleaned Product Dim Dataset'!$A:$G, 4, 0) -> Computer | T5: =VLOOKUP(D5, 'Cleaned Product Dim Dataset'!$A:$G, 5, 0) -> Larson Ltd
A6: SALE4 | B6: 45297 | C6: CUST1493 | D6: PROD59 | E6: STORE5 | F6: 3 | G6: 745.3 | H6: 0.18 | I6: Credit Card | J6: 1833.44 | K6: =VLOOKUP(C6,'Cleaned Customer_Dim'!$A$2:$H$501,4,0) -> Male | L6: =VLOOKUP(C6, 'Cleaned Customer_Dim'!$A:$F, 6, FALSE) -> Alabama | M6: =VLOOKUP(E6, 'Cleaned Stoer_ Dim'!$A$1:$E$21, 2, 0) -> Gray Ltd | N6: =VLOOKUP(E6, 'Cleaned Stoer_ Dim'!$A:$E,3, 0) -> North | O6: =VLOOKUP(E6, 'Cleaned Stoer_ Dim'!$A:$E, 4, 0) -> New Michaelchester | P6: =VLOOKUP(E6, 'Cleaned Stoer_ Dim'!$A:$E, 5, 0) -> Outlet | Q6: =VLOOKUP(D6, 'Cleaned Product Dim Dataset'!$A:$G, 2, 0) -> Men's Hair Styling Gel | R6: =VLOOKUP(D6, 'Cleaned Product Dim Dataset'!$A:$G, 3, 0) -> Beauty | S6: =VLOOKUP(D6, 'Cleaned Product Dim Dataset'!$A:$G, 4, 0) -> Haircare | T6: =VLOOKUP(D6, 'Cleaned Product Dim Dataset'!$A:$G, 5, 0) -> Cline-Mccarthy
A7: SALE5 | B7: 45499 | C7: CUST1116 | D7: PROD15 | E7: STORE7 | F7: 3 | G7: 147.01 | H7: 0.19 | I7: COD | J7: 357.23 | K7: =VLOOKUP(C7,'Cleaned Customer_Dim'!$A$2:$H$501,4,0) -> Female | L7: =VLOOKUP(C7, 'Cleaned Customer_Dim'!$A:$F, 6, FALSE) -> Rhode Island | M7: =VLOOKUP(E7, 'Cleaned Stoer_ Dim'!$A$1:$E$21, 2, 0) -> Martinez-Mullins | N7: =VLOOKUP(E7, 'Cleaned Stoer_ Dim'!$A:$E,3, 0) -> South | O7: =VLOOKUP(E7, 'Cleaned Stoer_ Dim'!$A:$E, 4, 0) -> Williamsfurt | P7: =VLOOKUP(E7, 'Cleaned Stoer_ Dim'!$A:$E, 5, 0) -> Online | Q7: =VLOOKUP(D7, 'Cleaned Product Dim Dataset'!$A:$G, 2, 0) -> 4K Home Projector | R7: =VLOOKUP(D7, 'Cleaned Product Dim Dataset'!$A:$G, 3, 0) -> Electronics | S7: =VLOOKUP(D7, 'Cleaned Product Dim Dataset'!$A:$G, 4, 0) -> Appliances | T7: =VLOOKUP(D7, 'Cleaned Product Dim Dataset'!$A:$G, 5, 0) -> Thomas LLC
A8: SALE6 | B8: 45850 | C8: CUST1016 | D8: PROD56 | E8: STORE4 | F8: 2 | G8: 785.31 | H8: 0.15 | I8: PayPal | J8: 1335.03 | K8: =VLOOKUP(C8,'Cleaned Customer_Dim'!$A$2:$H$501,4,0) -> Female | L8: =VLOOKUP(C8, 'Cleaned Customer_Dim'!$A:$F, 6, FALSE) -> Pennsylvania | M8: =VLOOKUP(E8, 'Cleaned Stoer_ Dim'!$A$1:$E$21, 2, 0) -> Alexander Group | N8: =VLOOKUP(E8, 'Cleaned Stoer_ Dim'!$A:$E,3, 0) -> South | O8: =VLOOKUP(E8, 'Cleaned Stoer_ Dim'!$A:$E, 4, 0) -> Port Sharon | P8: =VLOOKUP(E8, 'Cleaned Stoer_ Dim'!$A:$E, 5, 0) -> Online | Q8: =VLOOKUP(D8, 'Cleaned Product Dim Dataset'!$A:$G, 2, 0) -> Premium Blanket Throw | R8: =VLOOKUP(D8, 'Cleaned Product Dim Dataset'!$A:$G, 3, 0) -> Home | S8: =VLOOKUP(D8, 'Cleaned Product Dim Dataset'!$A:$G, 4, 0) -> Decor | T8: =VLOOKUP(D8, 'Cleaned Product Dim Dataset'!$A:$G, 5, 0) -> Hernandez, Kennedy and Porter
A9: SALE7 | B9: 45248 | C9: CUST1152 | D9: PROD70 | E9: STORE8 | F9: 4 | G9: 342.39 | H9: 0.23 | I9: PayPal | J9: 1054.56 | K9: =VLOOKUP(C9,'Cleaned Customer_Dim'!$A$2:$H$501,4,0) -> Female | L9: =VLOOKUP(C9, 'Cleaned Customer_Dim'!$A:$F, 6, FALSE) -> Missouri | M9: =VLOOKUP(E9, 'Cleaned Stoer_ Dim'!$A$1:$E$21, 2, 0) -> Bean, Jones and Park | N9: =VLOOKUP(E9, 'Cleaned Stoer_ Dim'!$A:$E,3, 0) -> West | O9: =VLOOKUP(E9, 'Cleaned Stoer_ Dim'!$A:$E, 4, 0) -> Thompsonborough | P9: =VLOOKUP(E9, 'Cleaned Stoer_ Dim'!$A:$E, 5, 0) -> Online | Q9: =VLOOKUP(D9, 'Cleaned Product Dim Dataset'!$A:$G, 2, 0) -> Kitchen Storage Rack | R9: =VLOOKUP(D9, 'Cleaned Product Dim Dataset'!$A:$G, 3, 0) -> Home | S9: =VLOOKUP(D9, 'Cleaned Product Dim Dataset'!$A:$G, 4, 0) -> Storage | T9: =VLOOKUP(D9, 'Cleaned Product Dim Dataset'!$A:$G, 5, 0) -> Duran Group
A10: SALE8 | B10: 45781 | C10: CUST1187 | D10: PROD99 | E10: STORE5 | F10: 2 | G10: 448.25 | H10: 0.07 | I10: PayPal | J10: 1250.62 | K10: =VLOOKUP(C10,'Cleaned Customer_Dim'!$A$2:$H$501,4,0) -> Female | L10: =VLOOKUP(C10, 'Cleaned Customer_Dim'!$A:$F, 6, FALSE) -> Alabama | M10: =VLOOKUP(E10, 'Cleaned Stoer_ Dim'!$A$1:$E$21, 2, 0) -> Gray Ltd | N10: =VLOOKUP(E10, 'Cleaned Stoer_ Dim'!$A:$E,3, 0) -> North | O10: =VLOOKUP(E10, 'Cleaned Stoer_ Dim'!$A:$E, 4, 0) -> New Michaelchester | P10: =VLOOKUP(E10, 'Cleaned Stoer_ Dim'!$A:$E, 5, 0) -> Outlet | Q10: =VLOOKUP(D10, 'Cleaned Product Dim Dataset'!$A:$G, 2, 0) -> Stainless Steel Cookware Set | R10: =VLOOKUP(D10, 'Cleaned Product Dim Dataset'!$A:$G, 3, 0) -> Home | S10: =VLOOKUP(D10, 'Cleaned Product Dim Dataset'!$A:$G, 4, 0) -> Kitchen | T10: =VLOOKUP(D10, 'Cleaned Product Dim Dataset'!$A:$G, 5, 0) -> Campbell Ltd
A11: SALE9 | B11: 45869 | C11: CUST1464 | D11: PROD33 | E11: STORE0 | F11: 2 | G11: 873.17 | H11: 0.23 | I11: PayPal | J11: 1344.68 | K11: =VLOOKUP(C11,'Cleaned Customer_Dim'!$A$2:$H$501,4,0) -> Female | L11: =VLOOKUP(C11, 'Cleaned Customer_Dim'!$A:$F, 6, FALSE) -> Washington | M11: =VLOOKUP(E11, 'Cleaned Stoer_ Dim'!$A$1:$E$21, 2, 0) -> Rivera-Warner | N11: =VLOOKUP(E11, 'Cleaned Stoer_ Dim'!$A:$E,3, 0) -> East | O11: =VLOOKUP(E11, 'Cleaned Stoer_ Dim'!$A:$E, 4, 0) -> Washingtonfurt | P11: =VLOOKUP(E11, 'Cleaned Stoer_ Dim'!$A:$E, 5, 0) -> Flagship | Q11: =VLOOKUP(D11, 'Cleaned Product Dim Dataset'!$A:$G, 2, 0) -> Modern Wall Clock | R11: =VLOOKUP(D11, 'Cleaned Product Dim Dataset'!$A:$G, 3, 0) -> Home | S11: =VLOOKUP(D11, 'Cleaned Product Dim Dataset'!$A:$G, 4, 0) -> Decor | T11: =VLOOKUP(D11, 'Cleaned Product Dim Dataset'!$A:$G, 5, 0) -> Weiss-Watson
A12: SALE10 | B12: 45335 | C12: CUST1065 | D12: PROD24 | E12: STORE14 | F12: 1 | G12: 278.63 | H12: 0.07 | I12: Credit Card | J12: 259.13 | K12: =VLOOKUP(C12,'Cleaned Customer_Dim'!$A$2:$H$501,4,0) -> Female | L12: =VLOOKUP(C12, 'Cleaned Customer_Dim'!$A:$F, 6, FALSE) -> Nevada | M12: =VLOOKUP(E12, 'Cleaned Stoer_ Dim'!$A$1:$E$21, 2, 0) -> Mcdonald Inc | N12: =VLOOKUP(E12, 'Cleaned Stoer_ Dim'!$A:$E,3, 0) -> South | O12: =VLOOKUP(E12, 'Cleaned Stoer_ Dim'!$A:$E, 4, 0) -> Christopherland | P12: =VLOOKUP(E12, 'Cleaned Stoer_ Dim'!$A:$E, 5, 0) -> Outlet | Q12: =VLOOKUP(D12, 'Cleaned Product Dim Dataset'!$A:$G, 2, 0) -> Foldable Camping Chair | R12: =VLOOKUP(D12, 'Cleaned Product Dim Dataset'!$A:$G, 3, 0) -> Sports | S12: =VLOOKUP(D12, 'Cleaned Product Dim Dataset'!$A:$G, 4, 0) -> Outdoor | T12: =VLOOKUP(D12, 'Cleaned Product Dim Dataset'!$A:$G, 5, 0) -> Cook Ltd
A13: SALE11 | B13: 45801 | C13: CUST1320 | D13: PROD39 | E13: STORE1 | F13: 4 | G13: 286.92 | H13: 0.17 | I13: Credit Card | J13: 952.57 | K13: =VLOOKUP(C13,'Cleaned Customer_Dim'!$A$2:$H$501,4,0) -> Female | L13: =VLOOKUP(C13, 'Cleaned Customer_Dim'!$A:$F, 6, FALSE) -> Iowa | M13: =VLOOKUP(E13, 'Cleaned Stoer_ Dim'!$A$1:$E$21, 2, 0) -> Martinez, Adkins and Johnson | N13: =VLOOKUP(E13, 'Cleaned Stoer_ Dim'!$A:$E,3, 0) -> North | O13: =VLOOKUP(E13, 'Cleaned Stoer_ Dim'!$A:$E, 4, 0) -> Danielmouth | P13: =VLOOKUP(E13, 'Cleaned Stoer_ Dim'!$A:$E, 5, 0) -> Flagship | Q13: =VLOOKUP(D13, 'Cleaned Product Dim Dataset'!$A:$G, 2, 0) -> Portable Power Bank | R13: =VLOOKUP(D13, 'Cleaned Product Dim Dataset'!$A:$G, 3, 0) -> Electronics | S13: =VLOOKUP(D13, 'Cleaned Product Dim Dataset'!$A:$G, 4, 0) -> Mobile | T13: =VLOOKUP(D13, 'Cleaned Product Dim Dataset'!$A:$G, 5, 0) -> Cummings and Sons
... A27: SALE25 | B27: 45552 | C27: CUST1381 | D27: PROD5 | E27: STORE3 | F27: 4 | G27: 852.71 | H27: 0.14 | I27: PayPal | J27: 2933.32 | K27: =VLOOKUP(C27,'Cleaned Customer_Dim'!$A$2:$H$501,4,0) -> Male | L27: =VLOOKUP(C27, 'Cleaned Customer_Dim'!$A:$F, 6, FALSE) -> Alabama | M27: =VLOOKUP(E27, 'Cleaned Stoer_ Dim'!$A$1:$E$21, 2, 0) -> Johnson-Wright | N27: =VLOOKUP(E27, 'Cleaned Stoer_ Dim'!$A:$E,3, 0) -> North | O27: =VLOOKUP(E27, 'Cleaned Stoer_ Dim'!$A:$E, 4, 0) -> Hoodberg | P27: =VLOOKUP(E27, 'Cleaned Stoer_ Dim'!$A:$E, 5, 0) -> Outlet | Q27: =VLOOKUP(D27, 'Cleaned Product Dim Dataset'!$A:$G, 2, 0) -> Men's Leather Belt | R27: =VLOOKUP(D27, 'Cleaned Product Dim Dataset'!$A:$G, 3, 0) -> Clothing | S27: =VLOOKUP(D27, 'Cleaned Product Dim Dataset'!$A:$G, 4, 0) -> Accessories | T27: =VLOOKUP(D27, 'Cleaned Product Dim Dataset'!$A:$G, 5, 0) -> Baldwin, Garza and Gonzalez
A28: SALE26 | B28: 45294 | C28: CUST1213 | D28: PROD98 | E28: STORE8 | F28: 4 | G28: 156.16 | H28: =1-(J28/(F28*G28)) -> 0.040007044 | I28: Credit Card | J28: 599.65 | K28: =VLOOKUP(C28,'Cleaned Customer_Dim'!$A$2:$H$501,4,0) -> Female | L28: =VLOOKUP(C28, 'Cleaned Customer_Dim'!$A:$F, 6, FALSE) -> North Dakota | M28: =VLOOKUP(E28, 'Cleaned Stoer_ Dim'!$A$1:$E$21, 2, 0) -> Bean, Jones and Park | N28: =VLOOKUP(E28, 'Cleaned Stoer_ Dim'!$A:$E,3, 0) -> West | O28: =VLOOKUP(E28, 'Cleaned Stoer_ Dim'!$A:$E, 4, 0) -> Thompsonborough | P28: =VLOOKUP(E28, 'Cleaned Stoer_ Dim'!$A:$E, 5, 0) -> Online | Q28: =VLOOKUP(D28, 'Cleaned Product Dim Dataset'!$A:$G, 2, 0) -> Portable Bluetooth Speaker | R28: =VLOOKUP(D28, 'Cleaned Product Dim Dataset'!$A:$G, 3, 0) -> Electronics | S28: =VLOOKUP(D28, 'Cleaned Product Dim Dataset'!$A:$G, 4, 0) -> Audio | T28: =VLOOKUP(D28, 'Cleaned Product Dim Dataset'!$A:$G, 5, 0) -> Flores-King
A29: SALE27 | B29: 45710 | C29: CUST1200 | D29: PROD77 | E29: STORE8 | F29: 3 | G29: 815.49 | H29: 0.17 | I29: Credit Card | J29: 2030.57 | K29: =VLOOKUP(C29,'Cleaned Customer_Dim'!$A$2:$H$501,4,0) -> Male | L29: =VLOOKUP(C29, 'Cleaned Customer_Dim'!$A:$F, 6, FALSE) -> Maine | M29: =VLOOKUP(E29, 'Cleaned Stoer_ Dim'!$A$1:$E$21, 2, 0) -> Bean, Jones and Park | N29: =VLOOKUP(E29, 'Cleaned Stoer_ Dim'!$A:$E,3, 0) -> West | O29: =VLOOKUP(E29, 'Cleaned Stoer_ Dim'!$A:$E, 4, 0) -> Thompsonborough | P29: =VLOOKUP(E29, 'Cleaned Stoer_ Dim'!$A:$E, 5, 0) -> Online | Q29: =VLOOKUP(D29, 'Cleaned Product Dim Dataset'!$A:$G, 2, 0) -> WiFi Mesh Router | R29: =VLOOKUP(D29, 'Cleaned Product Dim Dataset'!$A:$G, 3, 0) -> Electronics | S29: =VLOOKUP(D29, 'Cleaned Product Dim Dataset'!$A:$G, 4, 0) -> Appliances | T29: =VLOOKUP(D29, 'Cleaned Product Dim Dataset'!$A:$G, 5, 0) -> White, Reeves and Woods
A30: SALE28 | B30: 45923 | C30: CUST1148 | D30: PROD13 | E30: STORE2 | F30: 2 | G30: 74.21 | H30: 0.11 | I30: PayPal | J30: 132.09 | K30: =VLOOKUP(C30,'Cleaned Customer_Dim'!$A$2:$H$501,4,0) -> Female | L30: =VLOOKUP(C30, 'Cleaned Customer_Dim'!$A:$F, 6, FALSE) -> Wisconsin | M30: =VLOOKUP(E30, 'Cleaned Stoer_ Dim'!$A$1:$E$21, 2, 0) -> Black-Horn | N30: =VLOOKUP(E30, 'Cleaned Stoer_ Dim'!$A:$E,3, 0) -> South | O30: =VLOOKUP(E30, 'Cleaned Stoer_ Dim'!$A:$E, 4, 0) -> North Nancyview | P30: =VLOOKUP(E30, 'Cleaned Stoer_ Dim'!$A:$E, 5, 0) -> Outlet | Q30: =VLOOKUP(D30, 'Cleaned Product Dim Dataset'!$A:$G, 2, 0) -> USB-C Fast Charger | R30: =VLOOKUP(D30, 'Cleaned Product Dim Dataset'!$A:$G, 3, 0) -> Electronics | S30: =VLOOKUP(D30, 'Cleaned Product Dim Dataset'!$A:$G, 4, 0) -> Accessories | T30: =VLOOKUP(D30, 'Cleaned Product Dim Dataset'!$A:$G, 5, 0) -> Dawson-Perkins
A31: SALE29 | B31: 45302 | C31: CUST1348 | D31: PROD99 | E31: STORE3 | F31: 2 | G31: 451.67 | H31: 0.15 | I31: Credit Card | J31: 1535.68 | K31: =VLOOKUP(C31,'Cleaned Customer_Dim'!$A$2:$H$501,4,0) -> Male | L31: =VLOOKUP(C31, 'Cleaned Customer_Dim'!$A:$F, 6, FALSE) -> Pennsylvania | M31: =VLOOKUP(E31, 'Cleaned Stoer_ Dim'!$A$1:$E$21, 2, 0) -> Johnson-Wright | N31: =VLOOKUP(E31, 'Cleaned Stoer_ Dim'!$A:$E,3, 0) -> North | O31: =VLOOKUP(E31, 'Cleaned Stoer_ Dim'!$A:$E, 4, 0) -> Hoodberg | P31: =VLOOKUP(E31, 'Cleaned Stoer_ Dim'!$A:$E, 5, 0) -> Outlet | Q31: =VLOOKUP(D31, 'Cleaned Product Dim Dataset'!$A:$G, 2, 0) -> Stainless Steel Cookware Set | R31: =VLOOKUP(D31, 'Cleaned Product Dim Dataset'!$A:$G, 3, 0) -> Home | S31: =VLOOKUP(D31, 'Cleaned Product Dim Dataset'!$A:$G, 4, 0) -> Kitchen | T31: =VLOOKUP(D31, 'Cleaned Product Dim Dataset'!$A:$G, 5, 0) -> Campbell Ltd
A32: SALE30 | B32: 45217 | C32: CUST1028 | D32: PROD5 | E32: STORE19 | F32: 1 | G32: 429.38 | H32: 0.13 | I32: PayPal | J32: 373.56 | K32: =VLOOKUP(C32,'Cleaned Customer_Dim'!$A$2:$H$501,4,0) -> Female | L32: =VLOOKUP(C32, 'Cleaned Customer_Dim'!$A:$F, 6, FALSE) -> New Jersey | M32: =VLOOKUP(E32, 'Cleaned Stoer_ Dim'!$A$1:$E$21, 2, 0) -> Mann-Austin | N32: =VLOOKUP(E32, 'Cleaned Stoer_ Dim'!$A:$E,3, 0) -> East | O32: =VLOOKUP(E32, 'Cleaned Stoer_ Dim'!$A:$E, 4, 0) -> Vasquezborough | P32: =VLOOKUP(E32, 'Cleaned Stoer_ Dim'!$A:$E, 5, 0) -> Online | Q32: =VLOOKUP(D32, 'Cleaned Product Dim Dataset'!$A:$G, 2, 0) -> Men's Leather Belt | R32: =VLOOKUP(D32, 'Cleaned Product Dim Dataset'!$A:$G, 3, 0) -> Clothing | S32: =VLOOKUP(D32, 'Cleaned Product Dim Dataset'!$A:$G, 4, 0) -> Accessories | T32: =VLOOKUP(D32, 'Cleaned Product Dim Dataset'!$A:$G, 5, 0) -> Baldwin, Garza and Gonzalez
A33: SALE31 | B33: 45593 | C33: CUST1412 | D33: PROD53 | E33: STORE12 | F33: 2 | G33: 148.96 | H33: 0.03 | I33: COD | J33: 288.98 | K33: =VLOOKUP(C33,'Cleaned Customer_Dim'!$A$2:$H$501,4,0) -> Female | L33: =VLOOKUP(C33, 'Cleaned Customer_Dim'!$A:$F, 6, FALSE) -> Michigan | M33: =VLOOKUP(E33, 'Cleaned Stoer_ Dim'!$A$1:$E$21, 2, 0) -> Thomas, Bridges and Harris | N33: =VLOOKUP(E33, 'Cleaned Stoer_ Dim'!$A:$E,3, 0) -> North | O33: =VLOOKUP(E33, 'Cleaned Stoer_ Dim'!$A:$E, 4, 0) -> Sabrinatown | P33: =VLOOKUP(E33, 'Cleaned Stoer_ Dim'!$A:$E, 5, 0) -> Online | Q33: =VLOOKUP(D33, 'Cleaned Product Dim Dataset'!$A:$G, 2, 0) -> Men's Track Pants | R33: =VLOOKUP(D33, 'Cleaned Product Dim Dataset'!$A:$G, 3, 0) -> Clothing | S33: =VLOOKUP(D33, 'Cleaned Product Dim Dataset'!$A:$G, 4, 0) -> Bottoms | T33: =VLOOKUP(D33, 'Cleaned Product Dim Dataset'!$A:$G, 5, 0) -> Hamilton, Woods and Walker
A34: SALE32 | B34: 45597 | C34: CUST1398 | D34: PROD75 | E34: STORE8 | F34: 4 | G34: 313.83 | H34: 0.08 | I34: Credit Card | J34: 1154.89 | K34: =VLOOKUP(C34,'Cleaned Customer_Dim'!$A$2:$H$501,4,0) -> Male | L34: =VLOOKUP(C34, 'Cleaned Customer_Dim'!$A:$F, 6, FALSE) -> New Hampshire | M34: =VLOOKUP(E34, 'Cleaned Stoer_ Dim'!$A$1:$E$21, 2, 0) -> Bean, Jones and Park | N34: =VLOOKUP(E34, 'Cleaned Stoer_ Dim'!$A:$E,3, 0) -> West | O34: =VLOOKUP(E34, 'Cleaned Stoer_ Dim'!$A:$E, 4, 0) -> Thompsonborough | P34: =VLOOKUP(E34, 'Cleaned Stoer_ Dim'!$A:$E, 5, 0) -> Online | Q34: =VLOOKUP(D34, 'Cleaned Product Dim Dataset'!$A:$G, 2, 0) -> Women's Ankle Boots | R34: =VLOOKUP(D34, 'Cleaned Product Dim Dataset'!$A:$G, 3, 0) -> Clothing | S34: =VLOOKUP(D34, 'Cleaned Product Dim Dataset'!$A:$G, 4, 0) -> Footwear | T34: =VLOOKUP(D34, 'Cleaned Product Dim Dataset'!$A:$G, 5, 0) -> Poole PLC
A35: SALE33 | B35: 45620 | C35: CUST1453 | D35: PROD12 | E35: STORE6 | F35: 2 | G35: 717.31 | H35: 0.15 | I35: Credit Card | J35: 1219.43 | K35: =VLOOKUP(C35,'Cleaned Customer_Dim'!$A$2:$H$501,4,0) -> Female | L35: =VLOOKUP(C35, 'Cleaned Customer_Dim'!$A:$F, 6, FALSE) -> Hawaii | M35: =VLOOKUP(E35, 'Cleaned Stoer_ Dim'!$A$1:$E$21, 2, 0) -> Benson-Elliott | N35: =VLOOKUP(E35, 'Cleaned Stoer_ Dim'!$A:$E,3, 0) -> East | O35: =VLOOKUP(E35, 'Cleaned Stoer_ Dim'!$A:$E, 4, 0) -> Port Josephberg | P35: =VLOOKUP(E35, 'Cleaned Stoer_ Dim'!$A:$E, 5, 0) -> Online | Q35: =VLOOKUP(D35, 'Cleaned Product Dim Dataset'!$A:$G, 2, 0) -> Hair Strengthening Shampoo | R35: =VLOOKUP(D35, 'Cleaned Product Dim Dataset'!$A:$G, 3, 0) -> Beauty | S35: =VLOOKUP(D35, 'Cleaned Product Dim Dataset'!$A:$G, 4, 0) -> Haircare | T35: =VLOOKUP(D35, 'Cleaned Product Dim Dataset'!$A:$G, 5, 0) -> Rice LLC
A36: SALE34 | B36: 45215 | C36: CUST1344 | D36: PROD79 | E36: STORE1 | F36: 2 | G36: 873.22 | H36: 0.18 | I36: Credit Card | J36: 2148.12 | K36: =VLOOKUP(C36,'Cleaned Customer_Dim'!$A$2:$H$501,4,0) -> Male | L36: =VLOOKUP(C36, 'Cleaned Customer_Dim'!$A:$F, 6, FALSE) -> New Mexico | M36: =VLOOKUP(E36, 'Cleaned Stoer_ Dim'!$A$1:$E$21, 2, 0) -> Martinez, Adkins and Johnson | N36: =VLOOKUP(E36, 'Cleaned Stoer_ Dim'!$A:$E,3, 0) -> North | O36: =VLOOKUP(E36, 'Cleaned Stoer_ Dim'!$A:$E, 4, 0) -> Danielmouth | P36: =VLOOKUP(E36, 'Cleaned Stoer_ Dim'!$A:$E, 5, 0) -> Flagship | Q36: =VLOOKUP(D36, 'Cleaned Product Dim Dataset'!$A:$G, 2, 0) -> Decorative Lamp Shade | R36: =VLOOKUP(D36, 'Cleaned Product Dim Dataset'!$A:$G, 3, 0) -> Home | S36: =VLOOKUP(D36, 'Cleaned Product Dim Dataset'!$A:$G, 4, 0) -> Lighting | T36: =VLOOKUP(D36, 'Cleaned Product Dim Dataset'!$A:$G, 5, 0) -> Ramirez-Hanson
A37: SALE35 | B37: 45878 | C37: CUST1218 | D37: PROD16 | E37: STORE3 | F37: 4 | G37: 109.36 | H37: 0.19 | I37: COD | J37: 354.33 | K37: =VLOOKUP(C37,'Cleaned Customer_Dim'!$A$2:$H$501,4,0) -> Male | L37: =VLOOKUP(C37, 'Cleaned Customer_Dim'!$A:$F, 6, FALSE) -> California | M37: =VLOOKUP(E37, 'Cleaned Stoer_ Dim'!$A$1:$E$21, 2, 0) -> Johnson-Wright | N37: =VLOOKUP(E37, 'Cleaned Stoer_ Dim'!$A:$E,3, 0) -> North | O37: =VLOOKUP(E37, 'Cleaned Stoer_ Dim'!$A:$E, 4, 0) -> Hoodberg | P37: =VLOOKUP(E37, 'Cleaned Stoer_ Dim'!$A:$E, 5, 0) -> Outlet | Q37: =VLOOKUP(D37, 'Cleaned Product Dim Dataset'!$A:$G, 2, 0) -> Beard Grooming Kit | R37: =VLOOKUP(D37, 'Cleaned Product Dim Dataset'!$A:$G, 3, 0) -> Beauty | S37: =VLOOKUP(D37, 'Cleaned Product Dim Dataset'!$A:$G, 4, 0) -> Grooming | T37: =VLOOKUP(D37, 'Cleaned Product Dim Dataset'!$A:$G, 5, 0) -> Erickson-Green
A38: SALE36 | B38: 45635 | C38: CUST1086 | D38: PROD5 | E38: STORE7 | F38: 3 | G38: 559.52 | H38: 0.16 | I38: PayPal | J38: 1409.99 | K38: =VLOOKUP(C38,'Cleaned Customer_Dim'!$A$2:$H$501,4,0) -> Female | L38: =VLOOKUP(C38, 'Cleaned Customer_Dim'!$A:$F, 6, FALSE) -> Mississippi | M38: =VLOOKUP(E38, 'Cleaned Stoer_ Dim'!$A$1:$E$21, 2, 0) -> Martinez-Mullins | N38: =VLOOKUP(E38, 'Cleaned Stoer_ Dim'!$A:$E,3, 0) -> South | O38: =VLOOKUP(E38, 'Cleaned Stoer_ Dim'!$A:$E, 4, 0) -> Williamsfurt | P38: =VLOOKUP(E38, 'Cleaned Stoer_ Dim'!$A:$E, 5, 0) -> Online | Q38: =VLOOKUP(D38, 'Cleaned Product Dim Dataset'!$A:$G, 2, 0) -> Men's Leather Belt | R38: =VLOOKUP(D38, 'Cleaned Product Dim Dataset'!$A:$G, 3, 0) -> Clothing | S38: =VLOOKUP(D38, 'Cleaned Product Dim Dataset'!$A:$G, 4, 0) -> Accessories | T38: =VLOOKUP(D38, 'Cleaned Product Dim Dataset'!$A:$G, 5, 0) -> Baldwin, Garza and Gonzalez
A39: SALE37 | B39: 45329 | C39: CUST1492 | D39: PROD10 | E39: STORE17 | F39: 3 | G39: 121.76 | H39: 0.27 | I39: PayPal | J39: 266.65 | K39: =VLOOKUP(C39,'Cleaned Customer_Dim'!$A$2:$H$501,4,0) -> Female | L39: =VLOOKUP(C39, 'Cleaned Customer_Dim'!$A:$F, 6, FALSE) -> Florida | M39: =VLOOKUP(E39, 'Cleaned Stoer_ Dim'!$A$1:$E$21, 2, 0) -> Holloway Ltd | N39: =VLOOKUP(E39, 'Cleaned Stoer_ Dim'!$A:$E,3, 0) -> North | O39: =VLOOKUP(E39, 'Cleaned Stoer_ Dim'!$A:$E, 4, 0) -> Bensonhaven | P39: =VLOOKUP(E39, 'Cleaned Stoer_ Dim'!$A:$E, 5, 0) -> Flagship | Q39: =VLOOKUP(D39, 'Cleaned Product Dim Dataset'!$A:$G, 2, 0) -> Ceramic Kitchen Bowl Set | R39: =VLOOKUP(D39, 'Cleaned Product Dim Dataset'!$A:$G, 3, 0) -> Home | S39: =VLOOKUP(D39, 'Cleaned Product Dim Dataset'!$A:$G, 4, 0) -> Kitchen | T39: =VLOOKUP(D39, 'Cleaned Product Dim Dataset'!$A:$G, 5, 0) -> Hamilton Group
A40: SALE38 | B40: 45378 | C40: CUST1189 | D40: PROD33 | E40: STORE13 | F40: 4 | G40: 735.32 | H40: 0.06 | I40: COD | J40: 2764.8 | K40: =VLOOKUP(C40,'Cleaned Customer_Dim'!$A$2:$H$501,4,0) -> Male | L40: =VLOOKUP(C40, 'Cleaned Customer_Dim'!$A:$F, 6, FALSE) -> Kentucky | M40: =VLOOKUP(E40, 'Cleaned Stoer_ Dim'!$A$1:$E$21, 2, 0) -> Gardner, Humphrey and Contreras | N40: =VLOOKUP(E40, 'Cleaned Stoer_ Dim'!$A:$E,3, 0) -> East | O40: =VLOOKUP(E40, 'Cleaned Stoer_ Dim'!$A:$E, 4, 0) -> Johnsonville | P40: =VLOOKUP(E40, 'Cleaned Stoer_ Dim'!$A:$E, 5, 0) -> Flagship | Q40: =VLOOKUP(D40, 'Cleaned Product Dim Dataset'!$A:$G, 2, 0) -> Modern Wall Clock | R40: =VLOOKUP(D40, 'Cleaned Product Dim Dataset'!$A:$G, 3, 0) -> Home | S40: =VLOOKUP(D40, 'Cleaned Product Dim Dataset'!$A:$G, 4, 0) -> Decor | T40: =VLOOKUP(D40, 'Cleaned Product Dim Dataset'!$A:$G, 5, 0) -> Weiss-Watson
... A53: SALE51 | B53: 45689 | C53: CUST1142 | D53: PROD69 | E53: STORE7 | F53: 3 | G53: 76.57 | H53: 0.26 | I53: Credit Card | J53: 169.99 | K53: =VLOOKUP(C53,'Cleaned Customer_Dim'!$A$2:$H$501,4,0) -> Male | L53: =VLOOKUP(C53, 'Cleaned Customer_Dim'!$A:$F, 6, FALSE) -> Montana | M53: =VLOOKUP(E53, 'Cleaned Stoer_ Dim'!$A$1:$E$21, 2, 0) -> Martinez-Mullins | N53: =VLOOKUP(E53, 'Cleaned Stoer_ Dim'!$A:$E,3, 0) -> South | O53: =VLOOKUP(E53, 'Cleaned Stoer_ Dim'!$A:$E, 4, 0) -> Williamsfurt | P53: =VLOOKUP(E53, 'Cleaned Stoer_ Dim'!$A:$E, 5, 0) -> Online | Q53: =VLOOKUP(D53, 'Cleaned Product Dim Dataset'!$A:$G, 2, 0) -> Men's Sports Shorts | R53: =VLOOKUP(D53, 'Cleaned Product Dim Dataset'!$A:$G, 3, 0) -> Clothing | S53: =VLOOKUP(D53, 'Cleaned Product Dim Dataset'!$A:$G, 4, 0) -> Bottoms | T53: =VLOOKUP(D53, 'Cleaned Product Dim Dataset'!$A:$G, 5, 0) -> Fitzpatrick Ltd
A54: SALE52 | B54: 45894 | C54: CUST1148 | D54: PROD89 | E54: STORE6 | F54: 3 | G54: 513.98 | H54: =1-(J54/(F54*G54)) -> 0.68477373 | I54: Credit Card | J54: 486.06 | K54: =VLOOKUP(C54,'Cleaned Customer_Dim'!$A$2:$H$501,4,0) -> Female | L54: =VLOOKUP(C54, 'Cleaned Customer_Dim'!$A:$F, 6, FALSE) -> Wisconsin | M54: =VLOOKUP(E54, 'Cleaned Stoer_ Dim'!$A$1:$E$21, 2, 0) -> Benson-Elliott | N54: =VLOOKUP(E54, 'Cleaned Stoer_ Dim'!$A:$E,3, 0) -> East | O54: =VLOOKUP(E54, 'Cleaned Stoer_ Dim'!$A:$E, 4, 0) -> Port Josephberg | P54: =VLOOKUP(E54, 'Cleaned Stoer_ Dim'!$A:$E, 5, 0) -> Online | Q54: =VLOOKUP(D54, 'Cleaned Product Dim Dataset'!$A:$G, 2, 0) -> Face Foundation Kit | R54: =VLOOKUP(D54, 'Cleaned Product Dim Dataset'!$A:$G, 3, 0) -> Beauty | S54: =VLOOKUP(D54, 'Cleaned Product Dim Dataset'!$A:$G, 4, 0) -> Makeup | T54: =VLOOKUP(D54, 'Cleaned Product Dim Dataset'!$A:$G, 5, 0) -> Taylor-Elliott
A55: SALE53 | B55: 45677 | C55: CUST1324 | D55: PROD20 | E55: STORE8 | F55: 1 | G55: 900.35 | H55: 0.13 | I55: COD | J55: 783.3 | K55: =VLOOKUP(C55,'Cleaned Customer_Dim'!$A$2:$H$501,4,0) -> Male | L55: =VLOOKUP(C55, 'Cleaned Customer_Dim'!$A:$F, 6, FALSE) -> Oklahoma | M55: =VLOOKUP(E55, 'Cleaned Stoer_ Dim'!$A$1:$E$21, 2, 0) -> Bean, Jones and Park | N55: =VLOOKUP(E55, 'Cleaned Stoer_ Dim'!$A:$E,3, 0) -> West | O55: =VLOOKUP(E55, 'Cleaned Stoer_ Dim'!$A:$E, 4, 0) -> Thompsonborough | P55: =VLOOKUP(E55, 'Cleaned Stoer_ Dim'!$A:$E, 5, 0) -> Online | Q55: =VLOOKUP(D55, 'Cleaned Product Dim Dataset'!$A:$G, 2, 0) -> Outdoor Sports Water Bottle | R55: =VLOOKUP(D55, 'Cleaned Product Dim Dataset'!$A:$G, 3, 0) -> Sports | S55: =VLOOKUP(D55, 'Cleaned Product Dim Dataset'!$A:$G, 4, 0) -> Accessories | T55: =VLOOKUP(D55, 'Cleaned Product Dim Dataset'!$A:$G, 5, 0) -> Soto-Ellis
A56: SALE54 | B56: 45706 | C56: CUST1095 | D56: PROD40 | E56: STORE10 | F56: 4 | G56: 428.09 | H56: 0.07 | I56: Credit Card | J56: 1592.49 | K56: =VLOOKUP(C56,'Cleaned Customer_Dim'!$A$2:$H$501,4,0) -> Female | L56: =VLOOKUP(C56, 'Cleaned Customer_Dim'!$A:$F, 6, FALSE) -> New York | M56: =VLOOKUP(E56, 'Cleaned Stoer_ Dim'!$A$1:$E$21, 2, 0) -> Hill, Wagner and Ballard | N56: =VLOOKUP(E56, 'Cleaned Stoer_ Dim'!$A:$E,3, 0) -> East | O56: =VLOOKUP(E56, 'Cleaned Stoer_ Dim'!$A:$E, 4, 0) -> East Davidville | P56: =VLOOKUP(E56, 'Cleaned Stoer_ Dim'!$A:$E, 5, 0) -> Online | Q56: =VLOOKUP(D56, 'Cleaned Product Dim Dataset'!$A:$G, 2, 0) -> Noise-Canceling Headphones | R56: =VLOOKUP(D56, 'Cleaned Product Dim Dataset'!$A:$G, 3, 0) -> Electronics | S56: =VLOOKUP(D56, 'Cleaned Product Dim Dataset'!$A:$G, 4, 0) -> Audio | T56: =VLOOKUP(D56, 'Cleaned Product Dim Dataset'!$A:$G, 5, 0) -> Taylor-Hart
A57: SALE55 | B57: 45589 | C57: CUST1416 | D57: PROD49 | E57: STORE11 | F57: 2 | G57: 559.71 | H57: 0.3 | I57: COD | J57: 783.59 | K57: =VLOOKUP(C57,'Cleaned Customer_Dim'!$A$2:$H$501,4,0) -> Male | L57: =VLOOKUP(C57, 'Cleaned Customer_Dim'!$A:$F, 6, FALSE) -> Wisconsin | M57: =VLOOKUP(E57, 'Cleaned Stoer_ Dim'!$A$1:$E$21, 2, 0) -> Aguirre-Keller | N57: =VLOOKUP(E57, 'Cleaned Stoer_ Dim'!$A:$E,3, 0) -> South | O57: =VLOOKUP(E57, 'Cleaned Stoer_ Dim'!$A:$E, 4, 0) -> Lake Michael | P57: =VLOOKUP(E57, 'Cleaned Stoer_ Dim'!$A:$E, 5, 0) -> Online | Q57: =VLOOKUP(D57, 'Cleaned Product Dim Dataset'!$A:$G, 2, 0) -> Men's Roll-On Perfume | R57: =VLOOKUP(D57, 'Cleaned Product Dim Dataset'!$A:$G, 3, 0) -> Beauty | S57: =VLOOKUP(D57, 'Cleaned Product Dim Dataset'!$A:$G, 4, 0) -> Fragrance | T57: =VLOOKUP(D57, 'Cleaned Product Dim Dataset'!$A:$G, 5, 0) -> Sullivan and Sons
A58: SALE56 | B58: 45282 | C58: CUST1080 | D58: PROD34 | E58: STORE6 | F58: 2 | G58: 833.7 | H58: 0.06 | I58: PayPal | J58: 1567.36 | K58: =VLOOKUP(C58,'Cleaned Customer_Dim'!$A$2:$H$501,4,0) -> Female | L58: =VLOOKUP(C58, 'Cleaned Customer_Dim'!$A:$F, 6, FALSE) -> New Mexico | M58: =VLOOKUP(E58, 'Cleaned Stoer_ Dim'!$A$1:$E$21, 2, 0) -> Benson-Elliott | N58: =VLOOKUP(E58, 'Cleaned Stoer_ Dim'!$A:$E,3, 0) -> East | O58: =VLOOKUP(E58, 'Cleaned Stoer_ Dim'!$A:$E, 4, 0) -> Port Josephberg | P58: =VLOOKUP(E58, 'Cleaned Stoer_ Dim'!$A:$E, 5, 0) -> Online | Q58: =VLOOKUP(D58, 'Cleaned Product Dim Dataset'!$A:$G, 2, 0) -> Gaming Mechanical Keyboard | R58: =VLOOKUP(D58, 'Cleaned Product Dim Dataset'!$A:$G, 3, 0) -> Electronics | S58: =VLOOKUP(D58, 'Cleaned Product Dim Dataset'!$A:$G, 4, 0) -> Computer | T58: =VLOOKUP(D58, 'Cleaned Product Dim Dataset'!$A:$G, 5, 0) -> Lucero LLC
A59: SALE57 | B59: 45462 | C59: CUST1467 | D59: PROD47 | E59: STORE14 | F59: 2 | G59: 680.16 | H59: 0.28 | I59: Credit Card | J59: 979.43 | K59: =VLOOKUP(C59,'Cleaned Customer_Dim'!$A$2:$H$501,4,0) -> Female | L59: =VLOOKUP(C59, 'Cleaned Customer_Dim'!$A:$F, 6, FALSE) -> Vermont | M59: =VLOOKUP(E59, 'Cleaned Stoer_ Dim'!$A$1:$E$21, 2, 0) -> Mcdonald Inc | N59: =VLOOKUP(E59, 'Cleaned Stoer_ Dim'!$A:$E,3, 0) -> South | O59: =VLOOKUP(E59, 'Cleaned Stoer_ Dim'!$A:$E, 4, 0) -> Christopherland | P59: =VLOOKUP(E59, 'Cleaned Stoer_ Dim'!$A:$E, 5, 0) -> Outlet | Q59: =VLOOKUP(D59, 'Cleaned Product Dim Dataset'!$A:$G, 2, 0) -> Makeup Brush Set | R59: =VLOOKUP(D59, 'Cleaned Product Dim Dataset'!$A:$G, 3, 0) -> Beauty | S59: =VLOOKUP(D59, 'Cleaned Product Dim Dataset'!$A:$G, 4, 0) -> Makeup | T59: =VLOOKUP(D59, 'Cleaned Product Dim Dataset'!$A:$G, 5, 0) -> Cook Inc
A60: SALE58 | B60: 45633 | C60: CUST1404 | D60: PROD15 | E60: STORE7 | F60: 4 | G60: 733.42 | H60: =1-(J60/(F60*G60)) -> 0.13000055 | I60: PayPal | J60: 2552.3 | K60: =VLOOKUP(C60,'Cleaned Customer_Dim'!$A$2:$H$501,4,0) -> Female | L60: =VLOOKUP(C60, 'Cleaned Customer_Dim'!$A:$F, 6, FALSE) -> Arkansas | M60: =VLOOKUP(E60, 'Cleaned Stoer_ Dim'!$A$1:$E$21, 2, 0) -> Martinez-Mullins | N60: =VLOOKUP(E60, 'Cleaned Stoer_ Dim'!$A:$E,3, 0) -> South | O60: =VLOOKUP(E60, 'Cleaned Stoer_ Dim'!$A:$E, 4, 0) -> Williamsfurt | P60: =VLOOKUP(E60, 'Cleaned Stoer_ Dim'!$A:$E, 5, 0) -> Online | Q60: =VLOOKUP(D60, 'Cleaned Product Dim Dataset'!$A:$G, 2, 0) -> 4K Home Projector | R60: =VLOOKUP(D60, 'Cleaned Product Dim Dataset'!$A:$G, 3, 0) -> Electronics | S60: =VLOOKUP(D60, 'Cleaned Product Dim Dataset'!$A:$G, 4, 0) -> Appliances | T60: =VLOOKUP(D60, 'Cleaned Product Dim Dataset'!$A:$G, 5, 0) -> Thomas LLC
A61: SALE59 | B61: 45257 | C61: CUST1367 | D61: PROD89 | E61: STORE11 | F61: 1 | G61: 996.33 | H61: 0.23 | I61: PayPal | J61: 767.17 | K61: =VLOOKUP(C61,'Cleaned Customer_Dim'!$A$2:$H$501,4,0) -> Male | L61: =VLOOKUP(C61, 'Cleaned Customer_Dim'!$A:$F, 6, FALSE) -> Ohio | M61: =VLOOKUP(E61, 'Cleaned Stoer_ Dim'!$A$1:$E$21, 2, 0) -> Aguirre-Keller | N61: =VLOOKUP(E61, 'Cleaned Stoer_ Dim'!$A:$E,3, 0) -> South | O61: =VLOOKUP(E61, 'Cleaned Stoer_ Dim'!$A:$E, 4, 0) -> Lake Michael | P61: =VLOOKUP(E61, 'Cleaned Stoer_ Dim'!$A:$E, 5, 0) -> Online | Q61: =VLOOKUP(D61, 'Cleaned Product Dim Dataset'!$A:$G, 2, 0) -> Face Foundation Kit | R61: =VLOOKUP(D61, 'Cleaned Product Dim Dataset'!$A:$G, 3, 0) -> Beauty | S61: =VLOOKUP(D61, 'Cleaned Product Dim Dataset'!$A:$G, 4, 0) -> Makeup | T61: =VLOOKUP(D61, 'Cleaned Product Dim Dataset'!$A:$G, 5, 0) -> Taylor-Elliott
A62: SALE60 | B62: 45854 | C62: CUST1408 | D62: PROD31 | E62: STORE10 | F62: 1 | G62: 198.83 | H62: 0.09 | I62: COD | J62: 180.94 | K62: =VLOOKUP(C62,'Cleaned Customer_Dim'!$A$2:$H$501,4,0) -> Male | L62: =VLOOKUP(C62, 'Cleaned Customer_Dim'!$A:$F, 6, FALSE) -> New Jersey | M62: =VLOOKUP(E62, 'Cleaned Stoer_ Dim'!$A$1:$E$21, 2, 0) -> Hill, Wagner and Ballard | N62: =VLOOKUP(E62, 'Cleaned Stoer_ Dim'!$A:$E,3, 0) -> East | O62: =VLOOKUP(E62, 'Cleaned Stoer_ Dim'!$A:$E, 4, 0) -> East Davidville | P62: =VLOOKUP(E62, 'Cleaned Stoer_ Dim'!$A:$E, 5, 0) -> Online | Q62: =VLOOKUP(D62, 'Cleaned Product Dim Dataset'!$A:$G, 2, 0) -> Basketball | R62: =VLOOKUP(D62, 'Cleaned Product Dim Dataset'!$A:$G, 3, 0) -> Sports | S62: =VLOOKUP(D62, 'Cleaned Product Dim Dataset'!$A:$G, 4, 0) -> Team Sports | T62: =VLOOKUP(D62, 'Cleaned Product Dim Dataset'!$A:$G, 5, 0) -> Nolan-Snow
A63: SALE61 | B63: 45716 | C63: CUST1239 | D63: PROD19 | E63: STORE7 | F63: 1 | G63: 374.92 | H63: 0.18 | I63: PayPal | J63: 307.43 | K63: =VLOOKUP(C63,'Cleaned Customer_Dim'!$A$2:$H$501,4,0) -> Female | L63: =VLOOKUP(C63, 'Cleaned Customer_Dim'!$A:$F, 6, FALSE) -> Nevada | M63: =VLOOKUP(E63, 'Cleaned Stoer_ Dim'!$A$1:$E$21, 2, 0) -> Martinez-Mullins | N63: =VLOOKUP(E63, 'Cleaned Stoer_ Dim'!$A:$E,3, 0) -> South | O63: =VLOOKUP(E63, 'Cleaned Stoer_ Dim'!$A:$E, 4, 0) -> Williamsfurt | P63: =VLOOKUP(E63, 'Cleaned Stoer_ Dim'!$A:$E, 5, 0) -> Online | Q63: =VLOOKUP(D63, 'Cleaned Product Dim Dataset'!$A:$G, 2, 0) -> Knee Support Brace | R63: =VLOOKUP(D63, 'Cleaned Product Dim Dataset'!$A:$G, 3, 0) -> Sports | S63: =VLOOKUP(D63, 'Cleaned Product Dim Dataset'!$A:$G, 4, 0) -> Equipment | T63: =VLOOKUP(D63, 'Cleaned Product Dim Dataset'!$A:$G, 5, 0) -> May-Reese
A64: SALE62 | B64: 45515 | C64: CUST1464 | D64: PROD93 | E64: STORE16 | F64: 1 | G64: 468.94 | H64: 0.12 | I64: Credit Card | J64: 412.67 | K64: =VLOOKUP(C64,'Cleaned Customer_Dim'!$A$2:$H$501,4,0) -> Female | L64: =VLOOKUP(C64, 'Cleaned Customer_Dim'!$A:$F, 6, FALSE) -> Washington | M64: =VLOOKUP(E64, 'Cleaned Stoer_ Dim'!$A$1:$E$21, 2, 0) -> Frederick-Wright | N64: =VLOOKUP(E64, 'Cleaned Stoer_ Dim'!$A:$E,3, 0) -> West | O64: =VLOOKUP(E64, 'Cleaned Stoer_ Dim'!$A:$E, 4, 0) -> New Jimmymouth | P64: =VLOOKUP(E64, 'Cleaned Stoer_ Dim'!$A:$E, 5, 0) -> Flagship | Q64: =VLOOKUP(D64, 'Cleaned Product Dim Dataset'!$A:$G, 2, 0) -> USB-C Laptop Charger | R64: =VLOOKUP(D64, 'Cleaned Product Dim Dataset'!$A:$G, 3, 0) -> Electronics | S64: =VLOOKUP(D64, 'Cleaned Product Dim Dataset'!$A:$G, 4, 0) -> Computer | T64: =VLOOKUP(D64, 'Cleaned Product Dim Dataset'!$A:$G, 5, 0) -> Martin LLC
A65: SALE63 | B65: 45927 | C65: CUST1126 | D65: PROD89 | E65: STORE12 | F65: 2 | G65: 121.37 | H65: 0.05 | I65: Credit Card | J65: 230.6 | K65: =VLOOKUP(C65,'Cleaned Customer_Dim'!$A$2:$H$501,4,0) -> Female | L65: =VLOOKUP(C65, 'Cleaned Customer_Dim'!$A:$F, 6, FALSE) -> Arizona | M65: =VLOOKUP(E65, 'Cleaned Stoer_ Dim'!$A$1:$E$21, 2, 0) -> Thomas, Bridges and Harris | N65: =VLOOKUP(E65, 'Cleaned Stoer_ Dim'!$A:$E,3, 0) -> North | O65: =VLOOKUP(E65, 'Cleaned Stoer_ Dim'!$A:$E, 4, 0) -> Sabrinatown | P65: =VLOOKUP(E65, 'Cleaned Stoer_ Dim'!$A:$E, 5, 0) -> Online | Q65: =VLOOKUP(D65, 'Cleaned Product Dim Dataset'!$A:$G, 2, 0) -> Face Foundation Kit | R65: =VLOOKUP(D65, 'Cleaned Product Dim Dataset'!$A:$G, 3, 0) -> Beauty | S65: =VLOOKUP(D65, 'Cleaned Product Dim Dataset'!$A:$G, 4, 0) -> Makeup | T65: =VLOOKUP(D65, 'Cleaned Product Dim Dataset'!$A:$G, 5, 0) -> Taylor-Elliott
A66: SALE64 | B66: 45914 | C66: CUST1255 | D66: PROD53 | E66: STORE10 | F66: 3 | G66: 480.06 | H66: 0.01 | I66: Credit Card | J66: =F66*G66*(1-H66) -> 1425.7782 | K66: =VLOOKUP(C66,'Cleaned Customer_Dim'!$A$2:$H$501,4,0) -> Male | L66: =VLOOKUP(C66, 'Cleaned Customer_Dim'!$A:$F, 6, FALSE) -> Ohio | M66: =VLOOKUP(E66, 'Cleaned Stoer_ Dim'!$A$1:$E$21, 2, 0) -> Hill, Wagner and Ballard | N66: =VLOOKUP(E66, 'Cleaned Stoer_ Dim'!$A:$E,3, 0) -> East | O66: =VLOOKUP(E66, 'Cleaned Stoer_ Dim'!$A:$E, 4, 0) -> East Davidville | P66: =VLOOKUP(E66, 'Cleaned Stoer_ Dim'!$A:$E, 5, 0) -> Online | Q66: =VLOOKUP(D66, 'Cleaned Product Dim Dataset'!$A:$G, 2, 0) -> Men's Track Pants | R66: =VLOOKUP(D66, 'Cleaned Product Dim Dataset'!$A:$G, 3, 0) -> Clothing | S66: =VLOOKUP(D66, 'Cleaned Product Dim Dataset'!$A:$G, 4, 0) -> Bottoms | T66: =VLOOKUP(D66, 'Cleaned Product Dim Dataset'!$A:$G, 5, 0) -> Hamilton, Woods and Walker
A67: SALE65 | B67: 45290 | C67: CUST1162 | D67: PROD99 | E67: STORE17 | F67: 2 | G67: 856.57 | H67: 0.24 | I67: Credit Card | J67: 1301.99 | K67: =VLOOKUP(C67,'Cleaned Customer_Dim'!$A$2:$H$501,4,0) -> Male | L67: =VLOOKUP(C67, 'Cleaned Customer_Dim'!$A:$F, 6, FALSE) -> Tennessee | M67: =VLOOKUP(E67, 'Cleaned Stoer_ Dim'!$A$1:$E$21, 2, 0) -> Holloway Ltd | N67: =VLOOKUP(E67, 'Cleaned Stoer_ Dim'!$A:$E,3, 0) -> North | O67: =VLOOKUP(E67, 'Cleaned Stoer_ Dim'!$A:$E, 4, 0) -> Bensonhaven | P67: =VLOOKUP(E67, 'Cleaned Stoer_ Dim'!$A:$E, 5, 0) -> Flagship | Q67: =VLOOKUP(D67, 'Cleaned Product Dim Dataset'!$A:$G, 2, 0) -> Stainless Steel Cookware Set | R67: =VLOOKUP(D67, 'Cleaned Product Dim Dataset'!$A:$G, 3, 0) -> Home | S67: =VLOOKUP(D67, 'Cleaned Product Dim Dataset'!$A:$G, 4, 0) -> Kitchen | T67: =VLOOKUP(D67, 'Cleaned Product Dim Dataset'!$A:$G, 5, 0) -> Campbell Ltd
A68: SALE66 | B68: 45213 | C68: CUST1269 | D68: PROD77 | E68: STORE2 | F68: 4 | G68: 814.25 | H68: 0.18 | I68: Credit Card | J68: 2670.74 | K68: =VLOOKUP(C68,'Cleaned Customer_Dim'!$A$2:$H$501,4,0) -> Female | L68: =VLOOKUP(C68, 'Cleaned Customer_Dim'!$A:$F, 6, FALSE) -> California | M68: =VLOOKUP(E68, 'Cleaned Stoer_ Dim'!$A$1:$E$21, 2, 0) -> Black-Horn | N68: =VLOOKUP(E68, 'Cleaned Stoer_ Dim'!$A:$E,3, 0) -> South | O68: =VLOOKUP(E68, 'Cleaned Stoer_ Dim'!$A:$E, 4, 0) -> North Nancyview | P68: =VLOOKUP(E68, 'Cleaned Stoer_ Dim'!$A:$E, 5, 0) -> Outlet | Q68: =VLOOKUP(D68, 'Cleaned Product Dim Dataset'!$A:$G, 2, 0) -> WiFi Mesh Router | R68: =VLOOKUP(D68, 'Cleaned Product Dim Dataset'!$A:$G, 3, 0) -> Electronics | S68: =VLOOKUP(D68, 'Cleaned Product Dim Dataset'!$A:$G, 4, 0) -> Appliances | T68: =VLOOKUP(D68, 'Cleaned Product Dim Dataset'!$A:$G, 5, 0) -> White, Reeves and Woods
A69: SALE67 | B69: 45255 | C69: CUST1483 | D69: PROD12 | E69: STORE2 | F69: 1 | G69: 989.17 | H69: 0.2 | I69: PayPal | J69: 791.34 | K69: =VLOOKUP(C69,'Cleaned Customer_Dim'!$A$2:$H$501,4,0) -> Male | L69: =VLOOKUP(C69, 'Cleaned Customer_Dim'!$A:$F, 6, FALSE) -> Nevada | M69: =VLOOKUP(E69, 'Cleaned Stoer_ Dim'!$A$1:$E$21, 2, 0) -> Black-Horn | N69: =VLOOKUP(E69, 'Cleaned Stoer_ Dim'!$A:$E,3, 0) -> South | O69: =VLOOKUP(E69, 'Cleaned Stoer_ Dim'!$A:$E, 4, 0) -> North Nancyview | P69: =VLOOKUP(E69, 'Cleaned Stoer_ Dim'!$A:$E, 5, 0) -> Outlet | Q69: =VLOOKUP(D69, 'Cleaned Product Dim Dataset'!$A:$G, 2, 0) -> Hair Strengthening Shampoo | R69: =VLOOKUP(D69, 'Cleaned Product Dim Dataset'!$A:$G, 3, 0) -> Beauty | S69: =VLOOKUP(D69, 'Cleaned Product Dim Dataset'!$A:$G, 4, 0) -> Haircare | T69: =VLOOKUP(D69, 'Cleaned Product Dim Dataset'!$A:$G, 5, 0) -> Rice LLC
A70: SALE68 | B70: 45270 | C70: CUST1372 | D70: PROD72 | E70: STORE10 | F70: 4 | G70: 62.48 | H70: 0.18 | I70: Credit Card | J70: 204.93 | K70: =VLOOKUP(C70,'Cleaned Customer_Dim'!$A$2:$H$501,4,0) -> Male | L70: =VLOOKUP(C70, 'Cleaned Customer_Dim'!$A:$F, 6, FALSE) -> Ohio | M70: =VLOOKUP(E70, 'Cleaned Stoer_ Dim'!$A$1:$E$21, 2, 0) -> Hill, Wagner and Ballard | N70: =VLOOKUP(E70, 'Cleaned Stoer_ Dim'!$A:$E,3, 0) -> East | O70: =VLOOKUP(E70, 'Cleaned Stoer_ Dim'!$A:$E, 4, 0) -> East Davidville | P70: =VLOOKUP(E70, 'Cleaned Stoer_ Dim'!$A:$E, 5, 0) -> Online | Q70: =VLOOKUP(D70, 'Cleaned Product Dim Dataset'!$A:$G, 2, 0) -> Professional Jump Rope | R70: =VLOOKUP(D70, 'Cleaned Product Dim Dataset'!$A:$G, 3, 0) -> Sports | S70: =VLOOKUP(D70, 'Cleaned Product Dim Dataset'!$A:$G, 4, 0) -> Fitness | T70: =VLOOKUP(D70, 'Cleaned Product Dim Dataset'!$A:$G, 5, 0) -> Davis PLC
A71: SALE69 | B71: 45897 | C71: CUST1423 | D71: PROD13 | E71: STORE16 | F71: 4 | G71: 561.24 | H71: 0.24 | I71: Credit Card | J71: 1706.17 | K71: =VLOOKUP(C71,'Cleaned Customer_Dim'!$A$2:$H$501,4,0) -> Male | L71: =VLOOKUP(C71, 'Cleaned Customer_Dim'!$A:$F, 6, FALSE) -> Kansas | M71: =VLOOKUP(E71, 'Cleaned Stoer_ Dim'!$A$1:$E$21, 2, 0) -> Frederick-Wright | N71: =VLOOKUP(E71, 'Cleaned Stoer_ Dim'!$A:$E,3, 0) -> West | O71: =VLOOKUP(E71, 'Cleaned Stoer_ Dim'!$A:$E, 4, 0) -> New Jimmymouth | P71: =VLOOKUP(E71, 'Cleaned Stoer_ Dim'!$A:$E, 5, 0) -> Flagship | Q71: =VLOOKUP(D71, 'Cleaned Product Dim Dataset'!$A:$G, 2, 0) -> USB-C Fast Charger | R71: =VLOOKUP(D71, 'Cleaned Product Dim Dataset'!$A:$G, 3, 0) -> Electronics | S71: =VLOOKUP(D71, 'Cleaned Product Dim Dataset'!$A:$G, 4, 0) -> Accessories | T71: =VLOOKUP(D71, 'Cleaned Product Dim Dataset'!$A:$G, 5, 0) -> Dawson-Perkins
A72: SALE70 | B72: 45849 | C72: CUST1058 | D72: PROD60 | E72: STORE5 | F72: 3 | G72: 92.24 | H72: 0.28 | I72: COD | J72: =F72*G72*(1-H72) -> 199.2384 | K72: =VLOOKUP(C72,'Cleaned Customer_Dim'!$A$2:$H$501,4,0) -> Male | L72: =VLOOKUP(C72, 'Cleaned Customer_Dim'!$A:$F, 6, FALSE) -> Maryland | M72: =VLOOKUP(E72, 'Cleaned Stoer_ Dim'!$A$1:$E$21, 2, 0) -> Gray Ltd | N72: =VLOOKUP(E72, 'Cleaned Stoer_ Dim'!$A:$E,3, 0) -> North | O72: =VLOOKUP(E72, 'Cleaned Stoer_ Dim'!$A:$E, 4, 0) -> New Michaelchester | P72: =VLOOKUP(E72, 'Cleaned Stoer_ Dim'!$A:$E, 5, 0) -> Outlet | Q72: =VLOOKUP(D72, 'Cleaned Product Dim Dataset'!$A:$G, 2, 0) -> Luxury Perfume Spray | R72: =VLOOKUP(D72, 'Cleaned Product Dim Dataset'!$A:$G, 3, 0) -> Beauty | S72: =VLOOKUP(D72, 'Cleaned Product Dim Dataset'!$A:$G, 4, 0) -> Fragrance | T72: =VLOOKUP(D72, 'Cleaned Product Dim Dataset'!$A:$G, 5, 0) -> Gibson, Green and Lopez
A73: SALE71 | B73: 45889 | C73: CUST1168 | D73: PROD72 | E73: STORE1 | F73: 2 | G73: 668.3 | H73: 0.07 | I73: Credit Card | J73: 1243.04 | K73: =VLOOKUP(C73,'Cleaned Customer_Dim'!$A$2:$H$501,4,0) -> Female | L73: =VLOOKUP(C73, 'Cleaned Customer_Dim'!$A:$F, 6, FALSE) -> Florida | M73: =VLOOKUP(E73, 'Cleaned Stoer_ Dim'!$A$1:$E$21, 2, 0) -> Martinez, Adkins and Johnson | N73: =VLOOKUP(E73, 'Cleaned Stoer_ Dim'!$A:$E,3, 0) -> North | O73: =VLOOKUP(E73, 'Cleaned Stoer_ Dim'!$A:$E, 4, 0) -> Danielmouth | P73: =VLOOKUP(E73, 'Cleaned Stoer_ Dim'!$A:$E, 5, 0) -> Flagship | Q73: =VLOOKUP(D73, 'Cleaned Product Dim Dataset'!$A:$G, 2, 0) -> Professional Jump Rope | R73: =VLOOKUP(D73, 'Cleaned Product Dim Dataset'!$A:$G, 3, 0) -> Sports | S73: =VLOOKUP(D73, 'Cleaned Product Dim Dataset'!$A:$G, 4, 0) -> Fitness | T73: =VLOOKUP(D73, 'Cleaned Product Dim Dataset'!$A:$G, 5, 0) -> Davis PLC
A74: SALE72 | B74: 45533 | C74: CUST1409 | D74: PROD38 | E74: STORE5 | F74: 1 | G74: 553.82 | H74: 0.09 | I74: Credit Card | J74: 503.98 | K74: =VLOOKUP(C74,'Cleaned Customer_Dim'!$A$2:$H$501,4,0) -> Male | L74: =VLOOKUP(C74, 'Cleaned Customer_Dim'!$A:$F, 6, FALSE) -> Wyoming | M74: =VLOOKUP(E74, 'Cleaned Stoer_ Dim'!$A$1:$E$21, 2, 0) -> Gray Ltd | N74: =VLOOKUP(E74, 'Cleaned Stoer_ Dim'!$A:$E,3, 0) -> North | O74: =VLOOKUP(E74, 'Cleaned Stoer_ Dim'!$A:$E, 4, 0) -> New Michaelchester | P74: =VLOOKUP(E74, 'Cleaned Stoer_ Dim'!$A:$E, 5, 0) -> Outlet | Q74: =VLOOKUP(D74, 'Cleaned Product Dim Dataset'!$A:$G, 2, 0) -> Sports Water Hydration Pack | R74: =VLOOKUP(D74, 'Cleaned Product Dim Dataset'!$A:$G, 3, 0) -> Sports | S74: =VLOOKUP(D74, 'Cleaned Product Dim Dataset'!$A:$G, 4, 0) -> Outdoor | T74: =VLOOKUP(D74, 'Cleaned Product Dim Dataset'!$A:$G, 5, 0) -> Sims-Smith
A75: SALE73 | B75: 45626 | C75: CUST1037 | D75: PROD45 | E75: STORE11 | F75: 2 | G75: 556.43 | H75: 0.13 | I75: Credit Card | J75: 968.19 | K75: =VLOOKUP(C75,'Cleaned Customer_Dim'!$A$2:$H$501,4,0) -> Female | L75: =VLOOKUP(C75, 'Cleaned Customer_Dim'!$A:$F, 6, FALSE) -> South Dakota | M75: =VLOOKUP(E75, 'Cleaned Stoer_ Dim'!$A$1:$E$21, 2, 0) -> Aguirre-Keller | N75: =VLOOKUP(E75, 'Cleaned Stoer_ Dim'!$A:$E,3, 0) -> South | O75: =VLOOKUP(E75, 'Cleaned Stoer_ Dim'!$A:$E, 4, 0) -> Lake Michael | P75: =VLOOKUP(E75, 'Cleaned Stoer_ Dim'!$A:$E, 5, 0) -> Online | Q75: =VLOOKUP(D75, 'Cleaned Product Dim Dataset'!$A:$G, 2, 0) -> High-Grip Football | R75: =VLOOKUP(D75, 'Cleaned Product Dim Dataset'!$A:$G, 3, 0) -> Sports | S75: =VLOOKUP(D75, 'Cleaned Product Dim Dataset'!$A:$G, 4, 0) -> Team Sports | T75: =VLOOKUP(D75, 'Cleaned Product Dim Dataset'!$A:$G, 5, 0) -> Bridges, Banks and Cummings
A76: SALE74 | B76: 45942 | C76: CUST1273 | D76: PROD20 | E76: STORE8 | F76: 1 | G76: 184.98 | H76: 0.1 | I76: COD | J76: 166.48 | K76: =VLOOKUP(C76,'Cleaned Customer_Dim'!$A$2:$H$501,4,0) -> Male | L76: =VLOOKUP(C76, 'Cleaned Customer_Dim'!$A:$F, 6, FALSE) -> Mississippi | M76: =VLOOKUP(E76, 'Cleaned Stoer_ Dim'!$A$1:$E$21, 2, 0) -> Bean, Jones and Park | N76: =VLOOKUP(E76, 'Cleaned Stoer_ Dim'!$A:$E,3, 0) -> West | O76: =VLOOKUP(E76, 'Cleaned Stoer_ Dim'!$A:$E, 4, 0) -> Thompsonborough | P76: =VLOOKUP(E76, 'Cleaned Stoer_ Dim'!$A:$E, 5, 0) -> Online | Q76: =VLOOKUP(D76, 'Cleaned Product Dim Dataset'!$A:$G, 2, 0) -> Outdoor Sports Water Bottle | R76: =VLOOKUP(D76, 'Cleaned Product Dim Dataset'!$A:$G, 3, 0) -> Sports | S76: =VLOOKUP(D76, 'Cleaned Product Dim Dataset'!$A:$G, 4, 0) -> Accessories | T76: =VLOOKUP(D76, 'Cleaned Product Dim Dataset'!$A:$G, 5, 0) -> Soto-Ellis
A77: SALE75 | B77: 45500 | C77: CUST1035 | D77: PROD97 | E77: STORE12 | F77: 4 | G77: 700.18 | H77: 0.23 | I77: Credit Card | J77: 2156.55 | K77: =VLOOKUP(C77,'Cleaned Customer_Dim'!$A$2:$H$501,4,0) -> Male | L77: =VLOOKUP(C77, 'Cleaned Customer_Dim'!$A:$F, 6, FALSE) -> North Dakota | M77: =VLOOKUP(E77, 'Cleaned Stoer_ Dim'!$A$1:$E$21, 2, 0) -> Thomas, Bridges and Harris | N77: =VLOOKUP(E77, 'Cleaned Stoer_ Dim'!$A:$E,3, 0) -> North | O77: =VLOOKUP(E77, 'Cleaned Stoer_ Dim'!$A:$E, 4, 0) -> Sabrinatown | P77: =VLOOKUP(E77, 'Cleaned Stoer_ Dim'!$A:$E, 5, 0) -> Online | Q77: =VLOOKUP(D77, 'Cleaned Product Dim Dataset'!$A:$G, 2, 0) -> Cricket Bat | R77: =VLOOKUP(D77, 'Cleaned Product Dim Dataset'!$A:$G, 3, 0) -> Sports | S77: =VLOOKUP(D77, 'Cleaned Product Dim Dataset'!$A:$G, 4, 0) -> Team Sports | T77: =VLOOKUP(D77, 'Cleaned Product Dim Dataset'!$A:$G, 5, 0) -> Khan LLC
A78: SALE76 | B78: 45285 | C78: CUST1019 | D78: PROD76 | E78: STORE10 | F78: 2 | G78: 686.31 | H78: 0.25 | I78: Credit Card | J78: 1029.46 | K78: =VLOOKUP(C78,'Cleaned Customer_Dim'!$A$2:$H$501,4,0) -> Female | L78: =VLOOKUP(C78, 'Cleaned Customer_Dim'!$A:$F, 6, FALSE) -> New Jersey | M78: =VLOOKUP(E78, 'Cleaned Stoer_ Dim'!$A$1:$E$21, 2, 0) -> Hill, Wagner and Ballard | N78: =VLOOKUP(E78, 'Cleaned Stoer_ Dim'!$A:$E,3, 0) -> East | O78: =VLOOKUP(E78, 'Cleaned Stoer_ Dim'!$A:$E, 4, 0) -> East Davidville | P78: =VLOOKUP(E78, 'Cleaned Stoer_ Dim'!$A:$E, 5, 0) -> Online | Q78: =VLOOKUP(D78, 'Cleaned Product Dim Dataset'!$A:$G, 2, 0) -> Wireless Mouse | R78: =VLOOKUP(D78, 'Cleaned Product Dim Dataset'!$A:$G, 3, 0) -> Electronics | S78: =VLOOKUP(D78, 'Cleaned Product Dim Dataset'!$A:$G, 4, 0) -> Computer | T78: =VLOOKUP(D78, 'Cleaned Product Dim Dataset'!$A:$G, 5, 0) -> Larson Ltd
A79: SALE77 | B79: 45800 | C79: CUST1007 | D79: PROD67 | E79: STORE15 | F79: 1 | G79: 687.82 | H79: 0.27 | I79: COD | J79: 502.11 | K79: =VLOOKUP(C79,'Cleaned Customer_Dim'!$A$2:$H$501,4,0) -> Female | L79: =VLOOKUP(C79, 'Cleaned Customer_Dim'!$A:$F, 6, FALSE) -> West Virginia | M79: =VLOOKUP(E79, 'Cleaned Stoer_ Dim'!$A$1:$E$21, 2, 0) -> Shelton PLC | N79: =VLOOKUP(E79, 'Cleaned Stoer_ Dim'!$A:$E,3, 0) -> North | O79: =VLOOKUP(E79, 'Cleaned Stoer_ Dim'!$A:$E, 4, 0) -> East Jenniferstad | P79: =VLOOKUP(E79, 'Cleaned Stoer_ Dim'!$A:$E, 5, 0) -> Flagship | Q79: =VLOOKUP(D79, 'Cleaned Product Dim Dataset'!$A:$G, 2, 0) -> Smart LED Light Strip | R79: =VLOOKUP(D79, 'Cleaned Product Dim Dataset'!$A:$G, 3, 0) -> Electronics | S79: =VLOOKUP(D79, 'Cleaned Product Dim Dataset'!$A:$G, 4, 0) -> Accessories | T79: =VLOOKUP(D79, 'Cleaned Product Dim Dataset'!$A:$G, 5, 0) -> Flores-Davis
A80: SALE78 | B80: 45609 | C80: CUST1221 | D80: PROD83 | E80: STORE8 | F80: 2 | G80: 900.55 | H80: 0.16 | I80: Credit Card | J80: 1512.92 | K80: =VLOOKUP(C80,'Cleaned Customer_Dim'!$A$2:$H$501,4,0) -> Male | L80: =VLOOKUP(C80, 'Cleaned Customer_Dim'!$A:$F, 6, FALSE) -> Georgia | M80: =VLOOKUP(E80, 'Cleaned Stoer_ Dim'!$A$1:$E$21, 2, 0) -> Bean, Jones and Park | N80: =VLOOKUP(E80, 'Cleaned Stoer_ Dim'!$A:$E,3, 0) -> West | O80: =VLOOKUP(E80, 'Cleaned Stoer_ Dim'!$A:$E, 4, 0) -> Thompsonborough | P80: =VLOOKUP(E80, 'Cleaned Stoer_ Dim'!$A:$E, 5, 0) -> Online | Q80: =VLOOKUP(D80, 'Cleaned Product Dim Dataset'!$A:$G, 2, 0) -> Hydrating Face Cleanser | R80: =VLOOKUP(D80, 'Cleaned Product Dim Dataset'!$A:$G, 3, 0) -> Beauty | S80: =VLOOKUP(D80, 'Cleaned Product Dim Dataset'!$A:$G, 4, 0) -> Skincare | T80: =VLOOKUP(D80, 'Cleaned Product Dim Dataset'!$A:$G, 5, 0) -> Butler Group
A81: SALE79 | B81: 45268 | C81: CUST1115 | D81: PROD21 | E81: STORE2 | F81: 1 | G81: 341.17 | H81: 0.15 | I81: Credit Card | J81: 289.99 | K81: =VLOOKUP(C81,'Cleaned Customer_Dim'!$A$2:$H$501,4,0) -> Female | L81: =VLOOKUP(C81, 'Cleaned Customer_Dim'!$A:$F, 6, FALSE) -> North Dakota | M81: =VLOOKUP(E81, 'Cleaned Stoer_ Dim'!$A$1:$E$21, 2, 0) -> Black-Horn | N81: =VLOOKUP(E81, 'Cleaned Stoer_ Dim'!$A:$E,3, 0) -> South | O81: =VLOOKUP(E81, 'Cleaned Stoer_ Dim'!$A:$E, 4, 0) -> North Nancyview | P81: =VLOOKUP(E81, 'Cleaned Stoer_ Dim'!$A:$E, 5, 0) -> Outlet | Q81: =VLOOKUP(D81, 'Cleaned Product Dim Dataset'!$A:$G, 2, 0) -> Multi-Purpose Storage Box | R81: =VLOOKUP(D81, 'Cleaned Product Dim Dataset'!$A:$G, 3, 0) -> Home | S81: =VLOOKUP(D81, 'Cleaned Product Dim Dataset'!$A:$G, 4, 0) -> Storage | T81: =VLOOKUP(D81, 'Cleaned Product Dim Dataset'!$A:$G, 5, 0) -> Gardner-Montes
A82: SALE80 | B82: 45885 | C82: CUST1176 | D82: PROD52 | E82: STORE8 | F82: 1 | G82: 442.27 | H82: 0.06 | I82: COD | J82: 415.73 | K82: =VLOOKUP(C82,'Cleaned Customer_Dim'!$A$2:$H$501,4,0) -> Male | L82: =VLOOKUP(C82, 'Cleaned Customer_Dim'!$A:$F, 6, FALSE) -> Vermont | M82: =VLOOKUP(E82, 'Cleaned Stoer_ Dim'!$A$1:$E$21, 2, 0) -> Bean, Jones and Park | N82: =VLOOKUP(E82, 'Cleaned Stoer_ Dim'!$A:$E,3, 0) -> West | O82: =VLOOKUP(E82, 'Cleaned Stoer_ Dim'!$A:$E, 4, 0) -> Thompsonborough | P82: =VLOOKUP(E82, 'Cleaned Stoer_ Dim'!$A:$E, 5, 0) -> Online | Q82: =VLOOKUP(D82, 'Cleaned Product Dim Dataset'!$A:$G, 2, 0) -> Rugby Ball | R82: =VLOOKUP(D82, 'Cleaned Product Dim Dataset'!$A:$G, 3, 0) -> Sports | S82: =VLOOKUP(D82, 'Cleaned Product Dim Dataset'!$A:$G, 4, 0) -> Team Sports | T82: =VLOOKUP(D82, 'Cleaned Product Dim Dataset'!$A:$G, 5, 0) -> Harris Inc
A83: SALE81 | B83: 45616 | C83: CUST1253 | D83: PROD71 | E83: STORE9 | F83: 1 | G83: 363.73 | H83: 0.25 | I83: PayPal | J83: 272.8 | K83: =VLOOKUP(C83,'Cleaned Customer_Dim'!$A$2:$H$501,4,0) -> Male | L83: =VLOOKUP(C83, 'Cleaned Customer_Dim'!$A:$F, 6, FALSE) -> Wisconsin | M83: =VLOOKUP(E83, 'Cleaned Stoer_ Dim'!$A$1:$E$21, 2, 0) -> Moore, Padilla and Butler | N83: =VLOOKUP(E83, 'Cleaned Stoer_ Dim'!$A:$E,3, 0) -> South | O83: =VLOOKUP(E83, 'Cleaned Stoer_ Dim'!$A:$E, 4, 0) -> East Johnstad | P83: =VLOOKUP(E83, 'Cleaned Stoer_ Dim'!$A:$E, 5, 0) -> Flagship | Q83: =VLOOKUP(D83, 'Cleaned Product Dim Dataset'!$A:$G, 2, 0) -> Hair Repair Oil Treatment | R83: =VLOOKUP(D83, 'Cleaned Product Dim Dataset'!$A:$G, 3, 0) -> Beauty | S83: =VLOOKUP(D83, 'Cleaned Product Dim Dataset'!$A:$G, 4, 0) -> Haircare | T83: =VLOOKUP(D83, 'Cleaned Product Dim Dataset'!$A:$G, 5, 0) -> Hopkins Ltd
A84: SALE82 | B84: 45518 | C84: CUST1378 | D84: PROD91 | E84: STORE17 | F84: 2 | G84: 601.33 | H84: 0.16 | I84: PayPal | J84: 1010.23 | K84: =VLOOKUP(C84,'Cleaned Customer_Dim'!$A$2:$H$501,4,0) -> Female | L84: =VLOOKUP(C84, 'Cleaned Customer_Dim'!$A:$F, 6, FALSE) -> Delaware | M84: =VLOOKUP(E84, 'Cleaned Stoer_ Dim'!$A$1:$E$21, 2, 0) -> Holloway Ltd | N84: =VLOOKUP(E84, 'Cleaned Stoer_ Dim'!$A:$E,3, 0) -> North | O84: =VLOOKUP(E84, 'Cleaned Stoer_ Dim'!$A:$E, 4, 0) -> Bensonhaven | P84: =VLOOKUP(E84, 'Cleaned Stoer_ Dim'!$A:$E, 5, 0) -> Flagship | Q84: =VLOOKUP(D84, 'Cleaned Product Dim Dataset'!$A:$G, 2, 0) -> Women's High Heels | R84: =VLOOKUP(D84, 'Cleaned Product Dim Dataset'!$A:$G, 3, 0) -> Clothing | S84: =VLOOKUP(D84, 'Cleaned Product Dim Dataset'!$A:$G, 4, 0) -> Footwear | T84: =VLOOKUP(D84, 'Cleaned Product Dim Dataset'!$A:$G, 5, 0) -> Smith-Charles
A85: SALE83 | B85: 45427 | C85: CUST1403 | D85: PROD17 | E85: STORE18 | F85: 4 | G85: 34.39 | H85: 0.03 | I85: PayPal | J85: 133.43 | K85: =VLOOKUP(C85,'Cleaned Customer_Dim'!$A$2:$H$501,4,0) -> Male | L85: =VLOOKUP(C85, 'Cleaned Customer_Dim'!$A:$F, 6, FALSE) -> Louisiana | M85: =VLOOKUP(E85, 'Cleaned Stoer_ Dim'!$A$1:$E$21, 2, 0) -> Guerrero-Schmitt | N85: =VLOOKUP(E85, 'Cleaned Stoer_ Dim'!$A:$E,3, 0) -> East | O85: =VLOOKUP(E85, 'Cleaned Stoer_ Dim'!$A:$E, 4, 0) -> East Stevechester | P85: =VLOOKUP(E85, 'Cleaned Stoer_ Dim'!$A:$E, 5, 0) -> Flagship | Q85: =VLOOKUP(D85, 'Cleaned Product Dim Dataset'!$A:$G, 2, 0) -> Soccer Training Cone Set | R85: =VLOOKUP(D85, 'Cleaned Product Dim Dataset'!$A:$G, 3, 0) -> Sports | S85: =VLOOKUP(D85, 'Cleaned Product Dim Dataset'!$A:$G, 4, 0) -> Accessories | T85: =VLOOKUP(D85, 'Cleaned Product Dim Dataset'!$A:$G, 5, 0) -> Ford, Murphy and Wilson
A86: SALE84 | B86: 45268 | C86: CUST1423 | D86: PROD46 | E86: STORE17 | F86: 1 | G86: 773.57 | H86: 0.05 | I86: COD | J86: =F86*G86*(1-H86) -> 734.8915 | K86: =VLOOKUP(C86,'Cleaned Customer_Dim'!$A$2:$H$501,4,0) -> Male | L86: =VLOOKUP(C86, 'Cleaned Customer_Dim'!$A:$F, 6, FALSE) -> Kansas | M86: =VLOOKUP(E86, 'Cleaned Stoer_ Dim'!$A$1:$E$21, 2, 0) -> Holloway Ltd | N86: =VLOOKUP(E86, 'Cleaned Stoer_ Dim'!$A:$E,3, 0) -> North | O86: =VLOOKUP(E86, 'Cleaned Stoer_ Dim'!$A:$E, 4, 0) -> Bensonhaven | P86: =VLOOKUP(E86, 'Cleaned Stoer_ Dim'!$A:$E, 5, 0) -> Flagship | Q86: =VLOOKUP(D86, 'Cleaned Product Dim Dataset'!$A:$G, 2, 0) -> Men's Winter Jacket | R86: =VLOOKUP(D86, 'Cleaned Product Dim Dataset'!$A:$G, 3, 0) -> Clothing | S86: =VLOOKUP(D86, 'Cleaned Product Dim Dataset'!$A:$G, 4, 0) -> Outerwear | T86: =VLOOKUP(D86, 'Cleaned Product Dim Dataset'!$A:$G, 5, 0) -> Kelly, Smith and Perez
A87: SALE85 | B87: 45282 | C87: CUST1054 | D87: PROD88 | E87: STORE7 | F87: 4 | G87: 127.1 | H87: 0.24 | I87: COD | J87: 386.38 | K87: =VLOOKUP(C87,'Cleaned Customer_Dim'!$A$2:$H$501,4,0) -> Male | L87: =VLOOKUP(C87, 'Cleaned Customer_Dim'!$A:$F, 6, FALSE) -> Oklahoma | M87: =VLOOKUP(E87, 'Cleaned Stoer_ Dim'!$A$1:$E$21, 2, 0) -> Martinez-Mullins | N87: =VLOOKUP(E87, 'Cleaned Stoer_ Dim'!$A:$E,3, 0) -> South | O87: =VLOOKUP(E87, 'Cleaned Stoer_ Dim'!$A:$E, 4, 0) -> Williamsfurt | P87: =VLOOKUP(E87, 'Cleaned Stoer_ Dim'!$A:$E, 5, 0) -> Online | Q87: =VLOOKUP(D87, 'Cleaned Product Dim Dataset'!$A:$G, 2, 0) -> Sports Wrist Sweatbands | R87: =VLOOKUP(D87, 'Cleaned Product Dim Dataset'!$A:$G, 3, 0) -> Sports | S87: =VLOOKUP(D87, 'Cleaned Product Dim Dataset'!$A:$G, 4, 0) -> Accessories | T87: =VLOOKUP(D87, 'Cleaned Product Dim Dataset'!$A:$G, 5, 0) -> Olsen-Daniels
A88: SALE86 | B88: 45545 | C88: CUST1303 | D88: PROD20 | E88: STORE3 | F88: 3 | G88: 899.58 | H88: 0.28 | I88: PayPal | J88: 1943.09 | K88: =VLOOKUP(C88,'Cleaned Customer_Dim'!$A$2:$H$501,4,0) -> Female | L88: =VLOOKUP(C88, 'Cleaned Customer_Dim'!$A:$F, 6, FALSE) -> Delaware | M88: =VLOOKUP(E88, 'Cleaned Stoer_ Dim'!$A$1:$E$21, 2, 0) -> Johnson-Wright | N88: =VLOOKUP(E88, 'Cleaned Stoer_ Dim'!$A:$E,3, 0) -> North | O88: =VLOOKUP(E88, 'Cleaned Stoer_ Dim'!$A:$E, 4, 0) -> Hoodberg | P88: =VLOOKUP(E88, 'Cleaned Stoer_ Dim'!$A:$E, 5, 0) -> Outlet | Q88: =VLOOKUP(D88, 'Cleaned Product Dim Dataset'!$A:$G, 2, 0) -> Outdoor Sports Water Bottle | R88: =VLOOKUP(D88, 'Cleaned Product Dim Dataset'!$A:$G, 3, 0) -> Sports | S88: =VLOOKUP(D88, 'Cleaned Product Dim Dataset'!$A:$G, 4, 0) -> Accessories | T88: =VLOOKUP(D88, 'Cleaned Product Dim Dataset'!$A:$G, 5, 0) -> Soto-Ellis
A89: SALE87 | B89: 45755 | C89: CUST1327 | D89: PROD1 | E89: STORE10 | F89: 3 | G89: 964.39 | H89: 0.04 | I89: Credit Card | J89: 2777.44 | K89: =VLOOKUP(C89,'Cleaned Customer_Dim'!$A$2:$H$501,4,0) -> Female | L89: =VLOOKUP(C89, 'Cleaned Customer_Dim'!$A:$F, 6, FALSE) -> New York | M89: =VLOOKUP(E89, 'Cleaned Stoer_ Dim'!$A$1:$E$21, 2, 0) -> Hill, Wagner and Ballard | N89: =VLOOKUP(E89, 'Cleaned Stoer_ Dim'!$A:$E,3, 0) -> East | O89: =VLOOKUP(E89, 'Cleaned Stoer_ Dim'!$A:$E, 4, 0) -> East Davidville | P89: =VLOOKUP(E89, 'Cleaned Stoer_ Dim'!$A:$E, 5, 0) -> Online | Q89: =VLOOKUP(D89, 'Cleaned Product Dim Dataset'!$A:$G, 2, 0) -> Men's Graphic T-Shirt | R89: =VLOOKUP(D89, 'Cleaned Product Dim Dataset'!$A:$G, 3, 0) -> Clothing | S89: =VLOOKUP(D89, 'Cleaned Product Dim Dataset'!$A:$G, 4, 0) -> Tops | T89: =VLOOKUP(D89, 'Cleaned Product Dim Dataset'!$A:$G, 5, 0) -> Terry-Moore
A90: SALE88 | B90: 45588 | C90: CUST1183 | D90: PROD38 | E90: STORE0 | F90: 2 | G90: 217.83 | H90: 0.14 | I90: PayPal | J90: 374.67 | K90: =VLOOKUP(C90,'Cleaned Customer_Dim'!$A$2:$H$501,4,0) -> Male | L90: =VLOOKUP(C90, 'Cleaned Customer_Dim'!$A:$F, 6, FALSE) -> New York | M90: =VLOOKUP(E90, 'Cleaned Stoer_ Dim'!$A$1:$E$21, 2, 0) -> Rivera-Warner | N90: =VLOOKUP(E90, 'Cleaned Stoer_ Dim'!$A:$E,3, 0) -> East | O90: =VLOOKUP(E90, 'Cleaned Stoer_ Dim'!$A:$E, 4, 0) -> Washingtonfurt | P90: =VLOOKUP(E90, 'Cleaned Stoer_ Dim'!$A:$E, 5, 0) -> Flagship | Q90: =VLOOKUP(D90, 'Cleaned Product Dim Dataset'!$A:$G, 2, 0) -> Sports Water Hydration Pack | R90: =VLOOKUP(D90, 'Cleaned Product Dim Dataset'!$A:$G, 3, 0) -> Sports | S90: =VLOOKUP(D90, 'Cleaned Product Dim Dataset'!$A:$G, 4, 0) -> Outdoor | T90: =VLOOKUP(D90, 'Cleaned Product Dim Dataset'!$A:$G, 5, 0) -> Sims-Smith
A91: SALE89 | B91: 45848 | C91: CUST1143 | D91: PROD17 | E91: STORE1 | F91: 4 | G91: 187.71 | H91: 0.06 | I91: COD | J91: 705.79 | K91: =VLOOKUP(C91,'Cleaned Customer_Dim'!$A$2:$H$501,4,0) -> Male | L91: =VLOOKUP(C91, 'Cleaned Customer_Dim'!$A:$F, 6, FALSE) -> Alabama | M91: =VLOOKUP(E91, 'Cleaned Stoer_ Dim'!$A$1:$E$21, 2, 0) -> Martinez, Adkins and Johnson | N91: =VLOOKUP(E91, 'Cleaned Stoer_ Dim'!$A:$E,3, 0) -> North | O91: =VLOOKUP(E91, 'Cleaned Stoer_ Dim'!$A:$E, 4, 0) -> Danielmouth | P91: =VLOOKUP(E91, 'Cleaned Stoer_ Dim'!$A:$E, 5, 0) -> Flagship | Q91: =VLOOKUP(D91, 'Cleaned Product Dim Dataset'!$A:$G, 2, 0) -> Soccer Training Cone Set | R91: =VLOOKUP(D91, 'Cleaned Product Dim Dataset'!$A:$G, 3, 0) -> Sports | S91: =VLOOKUP(D91, 'Cleaned Product Dim Dataset'!$A:$G, 4, 0) -> Accessories | T91: =VLOOKUP(D91, 'Cleaned Product Dim Dataset'!$A:$G, 5, 0) -> Ford, Murphy and Wilson
A92: SALE90 | B92: 45577 | C92: CUST1010 | D92: PROD33 | E92: STORE18 | F92: 2 | G92: 350.12 | H92: 0.12 | I92: COD | J92: 616.21 | K92: =VLOOKUP(C92,'Cleaned Customer_Dim'!$A$2:$H$501,4,0) -> Male | L92: =VLOOKUP(C92, 'Cleaned Customer_Dim'!$A:$F, 6, FALSE) -> Pennsylvania | M92: =VLOOKUP(E92, 'Cleaned Stoer_ Dim'!$A$1:$E$21, 2, 0) -> Guerrero-Schmitt | N92: =VLOOKUP(E92, 'Cleaned Stoer_ Dim'!$A:$E,3, 0) -> East | O92: =VLOOKUP(E92, 'Cleaned Stoer_ Dim'!$A:$E, 4, 0) -> East Stevechester | P92: =VLOOKUP(E92, 'Cleaned Stoer_ Dim'!$A:$E, 5, 0) -> Flagship | Q92: =VLOOKUP(D92, 'Cleaned Product Dim Dataset'!$A:$G, 2, 0) -> Modern Wall Clock | R92: =VLOOKUP(D92, 'Cleaned Product Dim Dataset'!$A:$G, 3, 0) -> Home | S92: =VLOOKUP(D92, 'Cleaned Product Dim Dataset'!$A:$G, 4, 0) -> Decor | T92: =VLOOKUP(D92, 'Cleaned Product Dim Dataset'!$A:$G, 5, 0) -> Weiss-Watson
A93: SALE91 | B93: 45312 | C93: CUST1406 | D93: PROD16 | E93: STORE1 | F93: 4 | G93: 102.19 | H93: 0.17 | I93: PayPal | J93: 339.27 | K93: =VLOOKUP(C93,'Cleaned Customer_Dim'!$A$2:$H$501,4,0) -> Female | L93: =VLOOKUP(C93, 'Cleaned Customer_Dim'!$A:$F, 6, FALSE) -> Wisconsin | M93: =VLOOKUP(E93, 'Cleaned Stoer_ Dim'!$A$1:$E$21, 2, 0) -> Martinez, Adkins and Johnson | N93: =VLOOKUP(E93, 'Cleaned Stoer_ Dim'!$A:$E,3, 0) -> North | O93: =VLOOKUP(E93, 'Cleaned Stoer_ Dim'!$A:$E, 4, 0) -> Danielmouth | P93: =VLOOKUP(E93, 'Cleaned Stoer_ Dim'!$A:$E, 5, 0) -> Flagship | Q93: =VLOOKUP(D93, 'Cleaned Product Dim Dataset'!$A:$G, 2, 0) -> Beard Grooming Kit | R93: =VLOOKUP(D93, 'Cleaned Product Dim Dataset'!$A:$G, 3, 0) -> Beauty | S93: =VLOOKUP(D93, 'Cleaned Product Dim Dataset'!$A:$G, 4, 0) -> Grooming | T93: =VLOOKUP(D93, 'Cleaned Product Dim Dataset'!$A:$G, 5, 0) -> Erickson-Green
A94: SALE92 | B94: 45350 | C94: CUST1007 | D94: PROD86 | E94: STORE4 | F94: 1 | G94: 696.53 | H94: 0.17 | I94: Credit Card | J94: 578.12 | K94: =VLOOKUP(C94,'Cleaned Customer_Dim'!$A$2:$H$501,4,0) -> Female | L94: =VLOOKUP(C94, 'Cleaned Customer_Dim'!$A:$F, 6, FALSE) -> West Virginia | M94: =VLOOKUP(E94, 'Cleaned Stoer_ Dim'!$A$1:$E$21, 2, 0) -> Alexander Group | N94: =VLOOKUP(E94, 'Cleaned Stoer_ Dim'!$A:$E,3, 0) -> South | O94: =VLOOKUP(E94, 'Cleaned Stoer_ Dim'!$A:$E, 4, 0) -> Port Sharon | P94: =VLOOKUP(E94, 'Cleaned Stoer_ Dim'!$A:$E, 5, 0) -> Online | Q94: =VLOOKUP(D94, 'Cleaned Product Dim Dataset'!$A:$G, 2, 0) -> Kitchen Cutting Board | R94: =VLOOKUP(D94, 'Cleaned Product Dim Dataset'!$A:$G, 3, 0) -> Home | S94: =VLOOKUP(D94, 'Cleaned Product Dim Dataset'!$A:$G, 4, 0) -> Kitchen | T94: =VLOOKUP(D94, 'Cleaned Product Dim Dataset'!$A:$G, 5, 0) -> Taylor, Dodson and Johnston
A95: SALE93 | B95: 45657 | C95: CUST1065 | D95: PROD19 | E95: STORE4 | F95: 2 | G95: 327.52 | H95: 0.15 | I95: PayPal | J95: 556.78 | K95: =VLOOKUP(C95,'Cleaned Customer_Dim'!$A$2:$H$501,4,0) -> Female | L95: =VLOOKUP(C95, 'Cleaned Customer_Dim'!$A:$F, 6, FALSE) -> Nevada | M95: =VLOOKUP(E95, 'Cleaned Stoer_ Dim'!$A$1:$E$21, 2, 0) -> Alexander Group | N95: =VLOOKUP(E95, 'Cleaned Stoer_ Dim'!$A:$E,3, 0) -> South | O95: =VLOOKUP(E95, 'Cleaned Stoer_ Dim'!$A:$E, 4, 0) -> Port Sharon | P95: =VLOOKUP(E95, 'Cleaned Stoer_ Dim'!$A:$E, 5, 0) -> Online | Q95: =VLOOKUP(D95, 'Cleaned Product Dim Dataset'!$A:$G, 2, 0) -> Knee Support Brace | R95: =VLOOKUP(D95, 'Cleaned Product Dim Dataset'!$A:$G, 3, 0) -> Sports | S95: =VLOOKUP(D95, 'Cleaned Product Dim Dataset'!$A:$G, 4, 0) -> Equipment | T95: =VLOOKUP(D95, 'Cleaned Product Dim Dataset'!$A:$G, 5, 0) -> May-Reese
A96: SALE94 | B96: 45530 | C96: CUST1298 | D96: PROD97 | E96: STORE19 | F96: 2 | G96: 569.36 | H96: 0.01 | I96: PayPal | J96: =F96*G96*(1-H96) -> 1127.3328 | K96: =VLOOKUP(C96,'Cleaned Customer_Dim'!$A$2:$H$501,4,0) -> Male | L96: =VLOOKUP(C96, 'Cleaned Customer_Dim'!$A:$F, 6, FALSE) -> Maine | M96: =VLOOKUP(E96, 'Cleaned Stoer_ Dim'!$A$1:$E$21, 2, 0) -> Mann-Austin | N96: =VLOOKUP(E96, 'Cleaned Stoer_ Dim'!$A:$E,3, 0) -> East | O96: =VLOOKUP(E96, 'Cleaned Stoer_ Dim'!$A:$E, 4, 0) -> Vasquezborough | P96: =VLOOKUP(E96, 'Cleaned Stoer_ Dim'!$A:$E, 5, 0) -> Online | Q96: =VLOOKUP(D96, 'Cleaned Product Dim Dataset'!$A:$G, 2, 0) -> Cricket Bat | R96: =VLOOKUP(D96, 'Cleaned Product Dim Dataset'!$A:$G, 3, 0) -> Sports | S96: =VLOOKUP(D96, 'Cleaned Product Dim Dataset'!$A:$G, 4, 0) -> Team Sports | T96: =VLOOKUP(D96, 'Cleaned Product Dim Dataset'!$A:$G, 5, 0) -> Khan LLC
A97: SALE95 | B97: 45556 | C97: CUST1321 | D97: PROD99 | E97: STORE6 | F97: 2 | G97: 68.29 | H97: 0.14 | I97: COD | J97: 117.46 | K97: =VLOOKUP(C97,'Cleaned Customer_Dim'!$A$2:$H$501,4,0) -> Female | L97: =VLOOKUP(C97, 'Cleaned Customer_Dim'!$A:$F, 6, FALSE) -> Tennessee | M97: =VLOOKUP(E97, 'Cleaned Stoer_ Dim'!$A$1:$E$21, 2, 0) -> Benson-Elliott | N97: =VLOOKUP(E97, 'Cleaned Stoer_ Dim'!$A:$E,3, 0) -> East | O97: =VLOOKUP(E97, 'Cleaned Stoer_ Dim'!$A:$E, 4, 0) -> Port Josephberg | P97: =VLOOKUP(E97, 'Cleaned Stoer_ Dim'!$A:$E, 5, 0) -> Online | Q97: =VLOOKUP(D97, 'Cleaned Product Dim Dataset'!$A:$G, 2, 0) -> Stainless Steel Cookware Set | R97: =VLOOKUP(D97, 'Cleaned Product Dim Dataset'!$A:$G, 3, 0) -> Home | S97: =VLOOKUP(D97, 'Cleaned Product Dim Dataset'!$A:$G, 4, 0) -> Kitchen | T97: =VLOOKUP(D97, 'Cleaned Product Dim Dataset'!$A:$G, 5, 0) -> Campbell Ltd
A98: SALE96 | B98: 45523 | C98: CUST1244 | D98: PROD50 | E98: STORE10 | F98: 1 | G98: 842.9 | H98: 0.06 | I98: COD | J98: 792.33 | K98: =VLOOKUP(C98,'Cleaned Customer_Dim'!$A$2:$H$501,4,0) -> Male | L98: =VLOOKUP(C98, 'Cleaned Customer_Dim'!$A:$F, 6, FALSE) -> Utah | M98: =VLOOKUP(E98, 'Cleaned Stoer_ Dim'!$A$1:$E$21, 2, 0) -> Hill, Wagner and Ballard | N98: =VLOOKUP(E98, 'Cleaned Stoer_ Dim'!$A:$E,3, 0) -> East | O98: =VLOOKUP(E98, 'Cleaned Stoer_ Dim'!$A:$E, 4, 0) -> East Davidville | P98: =VLOOKUP(E98, 'Cleaned Stoer_ Dim'!$A:$E, 5, 0) -> Online | Q98: =VLOOKUP(D98, 'Cleaned Product Dim Dataset'!$A:$G, 2, 0) -> Boxing Hand Wraps | R98: =VLOOKUP(D98, 'Cleaned Product Dim Dataset'!$A:$G, 3, 0) -> Sports | S98: =VLOOKUP(D98, 'Cleaned Product Dim Dataset'!$A:$G, 4, 0) -> Fitness | T98: =VLOOKUP(D98, 'Cleaned Product Dim Dataset'!$A:$G, 5, 0) -> Smith-King
A99: SALE97 | B99: 45587 | C99: CUST1287 | D99: PROD3 | E99: STORE3 | F99: 3 | G99: 751.94 | H99: 0.26 | I99: PayPal | J99: 1669.31 | K99: =VLOOKUP(C99,'Cleaned Customer_Dim'!$A$2:$H$501,4,0) -> Female | L99: =VLOOKUP(C99, 'Cleaned Customer_Dim'!$A:$F, 6, FALSE) -> Vermont | M99: =VLOOKUP(E99, 'Cleaned Stoer_ Dim'!$A$1:$E$21, 2, 0) -> Johnson-Wright | N99: =VLOOKUP(E99, 'Cleaned Stoer_ Dim'!$A:$E,3, 0) -> North | O99: =VLOOKUP(E99, 'Cleaned Stoer_ Dim'!$A:$E, 4, 0) -> Hoodberg | P99: =VLOOKUP(E99, 'Cleaned Stoer_ Dim'!$A:$E, 5, 0) -> Outlet | Q99: =VLOOKUP(D99, 'Cleaned Product Dim Dataset'!$A:$G, 2, 0) -> Men's Running Jacket | R99: =VLOOKUP(D99, 'Cleaned Product Dim Dataset'!$A:$G, 3, 0) -> Clothing | S99: =VLOOKUP(D99, 'Cleaned Product Dim Dataset'!$A:$G, 4, 0) -> Outerwear | T99: =VLOOKUP(D99, 'Cleaned Product Dim Dataset'!$A:$G, 5, 0) -> Pineda Ltd
A100: SALE98 | B100: 45580 | C100: CUST1131 | D100: PROD56 | E100: STORE7 | F100: 4 | G100: 476.28 | H100: 0.17 | I100: Credit Card | J100: 1581.25 | K100: =VLOOKUP(C100,'Cleaned Customer_Dim'!$A$2:$H$501,4,0) -> Female | L100: =VLOOKUP(C100, 'Cleaned Customer_Dim'!$A:$F, 6, FALSE) -> Alabama | M100: =VLOOKUP(E100, 'Cleaned Stoer_ Dim'!$A$1:$E$21, 2, 0) -> Martinez-Mullins | N100: =VLOOKUP(E100, 'Cleaned Stoer_ Dim'!$A:$E,3, 0) -> South | O100: =VLOOKUP(E100, 'Cleaned Stoer_ Dim'!$A:$E, 4, 0) -> Williamsfurt | P100: =VLOOKUP(E100, 'Cleaned Stoer_ Dim'!$A:$E, 5, 0) -> Online | Q100: =VLOOKUP(D100, 'Cleaned Product Dim Dataset'!$A:$G, 2, 0) -> Premium Blanket Throw | R100: =VLOOKUP(D100, 'Cleaned Product Dim Dataset'!$A:$G, 3, 0) -> Home | S100: =VLOOKUP(D100, 'Cleaned Product Dim Dataset'!$A:$G, 4, 0) -> Decor | T100: =VLOOKUP(D100, 'Cleaned Product Dim Dataset'!$A:$G, 5, 0) -> Hernandez, Kennedy and Porter
A101: SALE99 | B101: 45479 | C101: CUST1325 | D101: PROD54 | E101: STORE3 | F101: 3 | G101: 541.99 | H101: 0.24 | I101: COD | J101: 1235.74 | K101: =VLOOKUP(C101,'Cleaned Customer_Dim'!$A$2:$H$501,4,0) -> Male | L101: =VLOOKUP(C101, 'Cleaned Customer_Dim'!$A:$F, 6, FALSE) -> Wisconsin | M101: =VLOOKUP(E101, 'Cleaned Stoer_ Dim'!$A$1:$E$21, 2, 0) -> Johnson-Wright | N101: =VLOOKUP(E101, 'Cleaned Stoer_ Dim'!$A:$E,3, 0) -> North | O101: =VLOOKUP(E101, 'Cleaned Stoer_ Dim'!$A:$E, 4, 0) -> Hoodberg | P101: =VLOOKUP(E101, 'Cleaned Stoer_ Dim'!$A:$E, 5, 0) -> Outlet | Q101: =VLOOKUP(D101, 'Cleaned Product Dim Dataset'!$A:$G, 2, 0) -> Sports Stopwatch Pro | R101: =VLOOKUP(D101, 'Cleaned Product Dim Dataset'!$A:$G, 3, 0) -> Sports | S101: =VLOOKUP(D101, 'Cleaned Product Dim Dataset'!$A:$G, 4, 0) -> Accessories | T101: =VLOOKUP(D101, 'Cleaned Product Dim Dataset'!$A:$G, 5, 0) -> Thompson-French
A102: SALE100 | B102: 45677 | C102: CUST1369 | D102: PROD33 | E102: STORE5 | F102: 2 | G102: 401.5 | H102: 0.18 | I102: Credit Card | J102: 658.46 | K102: =VLOOKUP(C102,'Cleaned Customer_Dim'!$A$2:$H$501,4,0) -> Female | L102: =VLOOKUP(C102, 'Cleaned Customer_Dim'!$A:$F, 6, FALSE) -> Vermont | M102: =VLOOKUP(E102, 'Cleaned Stoer_ Dim'!$A$1:$E$21, 2, 0) -> Gray Ltd | N102: =VLOOKUP(E102, 'Cleaned Stoer_ Dim'!$A:$E,3, 0) -> North | O102: =VLOOKUP(E102, 'Cleaned Stoer_ Dim'!$A:$E, 4, 0) -> New Michaelchester | P102: =VLOOKUP(E102, 'Cleaned Stoer_ Dim'!$A:$E, 5, 0) -> Outlet | Q102: =VLOOKUP(D102, 'Cleaned Product Dim Dataset'!$A:$G, 2, 0) -> Modern Wall Clock | R102: =VLOOKUP(D102, 'Cleaned Product Dim Dataset'!$A:$G, 3, 0) -> Home | S102: =VLOOKUP(D102, 'Cleaned Product Dim Dataset'!$A:$G, 4, 0) -> Decor | T102: =VLOOKUP(D102, 'Cleaned Product Dim Dataset'!$A:$G, 5, 0) -> Weiss-Watson
A103: SALE101 | B103: 45453 | C103: CUST1084 | D103: PROD25 | E103: STORE13 | F103: 3 | G103: 359.56 | H103: 0.17 | I103: PayPal | J103: 895.3 | K103: =VLOOKUP(C103,'Cleaned Customer_Dim'!$A$2:$H$501,4,0) -> Female | L103: =VLOOKUP(C103, 'Cleaned Customer_Dim'!$A:$F, 6, FALSE) -> Indiana | M103: =VLOOKUP(E103, 'Cleaned Stoer_ Dim'!$A$1:$E$21, 2, 0) -> Gardner, Humphrey and Contreras | N103: =VLOOKUP(E103, 'Cleaned Stoer_ Dim'!$A:$E,3, 0) -> East | O103: =VLOOKUP(E103, 'Cleaned Stoer_ Dim'!$A:$E, 4, 0) -> Johnsonville | P103: =VLOOKUP(E103, 'Cleaned Stoer_ Dim'!$A:$E, 5, 0) -> Flagship | Q103: =VLOOKUP(D103, 'Cleaned Product Dim Dataset'!$A:$G, 2, 0) -> Women's Scarf Set | R103: =VLOOKUP(D103, 'Cleaned Product Dim Dataset'!$A:$G, 3, 0) -> Clothing | S103: =VLOOKUP(D103, 'Cleaned Product Dim Dataset'!$A:$G, 4, 0) -> Accessories | T103: =VLOOKUP(D103, 'Cleaned Product Dim Dataset'!$A:$G, 5, 0) -> Brown and Sons
A104: SALE102 | B104: 45552 | C104: CUST1097 | D104: PROD80 | E104: STORE12 | F104: 2 | G104: 471.88 | H104: 0.24 | I104: PayPal | J104: 717.26 | K104: =VLOOKUP(C104,'Cleaned Customer_Dim'!$A$2:$H$501,4,0) -> Male | L104: =VLOOKUP(C104, 'Cleaned Customer_Dim'!$A:$F, 6, FALSE) -> South Dakota | M104: =VLOOKUP(E104, 'Cleaned Stoer_ Dim'!$A$1:$E$21, 2, 0) -> Thomas, Bridges and Harris | N104: =VLOOKUP(E104, 'Cleaned Stoer_ Dim'!$A:$E,3, 0) -> North | O104: =VLOOKUP(E104, 'Cleaned Stoer_ Dim'!$A:$E, 4, 0) -> Sabrinatown | P104: =VLOOKUP(E104, 'Cleaned Stoer_ Dim'!$A:$E, 5, 0) -> Online | Q104: =VLOOKUP(D104, 'Cleaned Product Dim Dataset'!$A:$G, 2, 0) -> Wall-Mounted Spice Rack | R104: =VLOOKUP(D104, 'Cleaned Product Dim Dataset'!$A:$G, 3, 0) -> Home | S104: =VLOOKUP(D104, 'Cleaned Product Dim Dataset'!$A:$G, 4, 0) -> Kitchen | T104: =VLOOKUP(D104, 'Cleaned Product Dim Dataset'!$A:$G, 5, 0) -> Allison Ltd
A105: SALE103 | B105: 45907 | C105: CUST1182 | D105: PROD34 | E105: STORE4 | F105: 4 | G105: 925.19 | H105: 0.19 | I105: PayPal | J105: 2997.62 | K105: =VLOOKUP(C105,'Cleaned Customer_Dim'!$A$2:$H$501,4,0) -> Female | L105: =VLOOKUP(C105, 'Cleaned Customer_Dim'!$A:$F, 6, FALSE) -> Oklahoma | M105: =VLOOKUP(E105, 'Cleaned Stoer_ Dim'!$A$1:$E$21, 2, 0) -> Alexander Group | N105: =VLOOKUP(E105, 'Cleaned Stoer_ Dim'!$A:$E,3, 0) -> South | O105: =VLOOKUP(E105, 'Cleaned Stoer_ Dim'!$A:$E, 4, 0) -> Port Sharon | P105: =VLOOKUP(E105, 'Cleaned Stoer_ Dim'!$A:$E, 5, 0) -> Online | Q105: =VLOOKUP(D105, 'Cleaned Product Dim Dataset'!$A:$G, 2, 0) -> Gaming Mechanical Keyboard | R105: =VLOOKUP(D105, 'Cleaned Product Dim Dataset'!$A:$G, 3, 0) -> Electronics | S105: =VLOOKUP(D105, 'Cleaned Product Dim Dataset'!$A:$G, 4, 0) -> Computer | T105: =VLOOKUP(D105, 'Cleaned Product Dim Dataset'!$A:$G, 5, 0) -> Lucero LLC
A106: SALE104 | B106: 45330 | C106: CUST1029 | D106: PROD86 | E106: STORE11 | F106: 2 | G106: 879.63 | H106: 0.07 | I106: COD | J106: 1636.11 | K106: =VLOOKUP(C106,'Cleaned Customer_Dim'!$A$2:$H$501,4,0) -> Female | L106: =VLOOKUP(C106, 'Cleaned Customer_Dim'!$A:$F, 6, FALSE) -> California | M106: =VLOOKUP(E106, 'Cleaned Stoer_ Dim'!$A$1:$E$21, 2, 0) -> Aguirre-Keller | N106: =VLOOKUP(E106, 'Cleaned Stoer_ Dim'!$A:$E,3, 0) -> South | O106: =VLOOKUP(E106, 'Cleaned Stoer_ Dim'!$A:$E, 4, 0) -> Lake Michael | P106: =VLOOKUP(E106, 'Cleaned Stoer_ Dim'!$A:$E, 5, 0) -> Online | Q106: =VLOOKUP(D106, 'Cleaned Product Dim Dataset'!$A:$G, 2, 0) -> Kitchen Cutting Board | R106: =VLOOKUP(D106, 'Cleaned Product Dim Dataset'!$A:$G, 3, 0) -> Home | S106: =VLOOKUP(D106, 'Cleaned Product Dim Dataset'!$A:$G, 4, 0) -> Kitchen | T106: =VLOOKUP(D106, 'Cleaned Product Dim Dataset'!$A:$G, 5, 0) -> Taylor, Dodson and Johnston
A107: SALE105 | B107: 45214 | C107: CUST1002 | D107: PROD79 | E107: STORE17 | F107: 2 | G107: 418.23 | H107: 0.28 | I107: Credit Card | J107: 602.25 | K107: =VLOOKUP(C107,'Cleaned Customer_Dim'!$A$2:$H$501,4,0) -> Female | L107: =VLOOKUP(C107, 'Cleaned Customer_Dim'!$A:$F, 6, FALSE) -> Alabama | M107: =VLOOKUP(E107, 'Cleaned Stoer_ Dim'!$A$1:$E$21, 2, 0) -> Holloway Ltd | N107: =VLOOKUP(E107, 'Cleaned Stoer_ Dim'!$A:$E,3, 0) -> North | O107: =VLOOKUP(E107, 'Cleaned Stoer_ Dim'!$A:$E, 4, 0) -> Bensonhaven | P107: =VLOOKUP(E107, 'Cleaned Stoer_ Dim'!$A:$E, 5, 0) -> Flagship | Q107: =VLOOKUP(D107, 'Cleaned Product Dim Dataset'!$A:$G, 2, 0) -> Decorative Lamp Shade | R107: =VLOOKUP(D107, 'Cleaned Product Dim Dataset'!$A:$G, 3, 0) -> Home | S107: =VLOOKUP(D107, 'Cleaned Product Dim Dataset'!$A:$G, 4, 0) -> Lighting | T107: =VLOOKUP(D107, 'Cleaned Product Dim Dataset'!$A:$G, 5, 0) -> Ramirez-Hanson
A108: SALE106 | B108: 45891 | C108: CUST1269 | D108: PROD19 | E108: STORE18 | F108: 3 | G108: 551.72 | H108: 0.03 | I108: COD | J108: 1605.51 | K108: =VLOOKUP(C108,'Cleaned Customer_Dim'!$A$2:$H$501,4,0) -> Female | L108: =VLOOKUP(C108, 'Cleaned Customer_Dim'!$A:$F, 6, FALSE) -> California | M108: =VLOOKUP(E108, 'Cleaned Stoer_ Dim'!$A$1:$E$21, 2, 0) -> Guerrero-Schmitt | N108: =VLOOKUP(E108, 'Cleaned Stoer_ Dim'!$A:$E,3, 0) -> East | O108: =VLOOKUP(E108, 'Cleaned Stoer_ Dim'!$A:$E, 4, 0) -> East Stevechester | P108: =VLOOKUP(E108, 'Cleaned Stoer_ Dim'!$A:$E, 5, 0) -> Flagship | Q108: =VLOOKUP(D108, 'Cleaned Product Dim Dataset'!$A:$G, 2, 0) -> Knee Support Brace | R108: =VLOOKUP(D108, 'Cleaned Product Dim Dataset'!$A:$G, 3, 0) -> Sports | S108: =VLOOKUP(D108, 'Cleaned Product Dim Dataset'!$A:$G, 4, 0) -> Equipment | T108: =VLOOKUP(D108, 'Cleaned Product Dim Dataset'!$A:$G, 5, 0) -> May-Reese
... A260: SALE258 | B260: 45300 | C260: CUST1136 | D260: PROD35 | E260: STORE17 | F260: 1 | G260: 222.94 | H260: 0.19 | I260: Credit Card | J260: 180.58 | K260: =VLOOKUP(C260,'Cleaned Customer_Dim'!$A$2:$H$501,4,0) -> Male | L260: =VLOOKUP(C260, 'Cleaned Customer_Dim'!$A:$F, 6, FALSE) -> Nebraska | M260: =VLOOKUP(E260, 'Cleaned Stoer_ Dim'!$A$1:$E$21, 2, 0) -> Holloway Ltd | N260: =VLOOKUP(E260, 'Cleaned Stoer_ Dim'!$A:$E,3, 0) -> North | O260: =VLOOKUP(E260, 'Cleaned Stoer_ Dim'!$A:$E, 4, 0) -> Bensonhaven | P260: =VLOOKUP(E260, 'Cleaned Stoer_ Dim'!$A:$E, 5, 0) -> Flagship | Q260: =VLOOKUP(D260, 'Cleaned Product Dim Dataset'!$A:$G, 2, 0) -> Bedroom Table Lamp | R260: =VLOOKUP(D260, 'Cleaned Product Dim Dataset'!$A:$G, 3, 0) -> Home | S260: =VLOOKUP(D260, 'Cleaned Product Dim Dataset'!$A:$G, 4, 0) -> Lighting | T260: =VLOOKUP(D260, 'Cleaned Product Dim Dataset'!$A:$G, 5, 0) -> Jones LLC
A261: SALE259 | B261: 45773 | C261: CUST1248 | D261: PROD35 | E261: STORE2 | F261: 2 | G261: 355.3 | H261: =1-(J261/(F261*G261)) -> 0.16999719 | I261: PayPal | J261: 589.8 | K261: =VLOOKUP(C261,'Cleaned Customer_Dim'!$A$2:$H$501,4,0) -> Male | L261: =VLOOKUP(C261, 'Cleaned Customer_Dim'!$A:$F, 6, FALSE) -> Nevada | M261: =VLOOKUP(E261, 'Cleaned Stoer_ Dim'!$A$1:$E$21, 2, 0) -> Black-Horn | N261: =VLOOKUP(E261, 'Cleaned Stoer_ Dim'!$A:$E,3, 0) -> South | O261: =VLOOKUP(E261, 'Cleaned Stoer_ Dim'!$A:$E, 4, 0) -> North Nancyview | P261: =VLOOKUP(E261, 'Cleaned Stoer_ Dim'!$A:$E, 5, 0) -> Outlet | Q261: =VLOOKUP(D261, 'Cleaned Product Dim Dataset'!$A:$G, 2, 0) -> Bedroom Table Lamp | R261: =VLOOKUP(D261, 'Cleaned Product Dim Dataset'!$A:$G, 3, 0) -> Home | S261: =VLOOKUP(D261, 'Cleaned Product Dim Dataset'!$A:$G, 4, 0) -> Lighting | T261: =VLOOKUP(D261, 'Cleaned Product Dim Dataset'!$A:$G, 5, 0) -> Jones LLC
A262: SALE260 | B262: 45497 | C262: CUST1103 | D262: PROD89 | E262: STORE19 | F262: 4 | G262: 611.3 | H262: 0.11 | I262: PayPal | J262: 2176.23 | K262: =VLOOKUP(C262,'Cleaned Customer_Dim'!$A$2:$H$501,4,0) -> Male | L262: =VLOOKUP(C262, 'Cleaned Customer_Dim'!$A:$F, 6, FALSE) -> Connecticut | M262: =VLOOKUP(E262, 'Cleaned Stoer_ Dim'!$A$1:$E$21, 2, 0) -> Mann-Austin | N262: =VLOOKUP(E262, 'Cleaned Stoer_ Dim'!$A:$E,3, 0) -> East | O262: =VLOOKUP(E262, 'Cleaned Stoer_ Dim'!$A:$E, 4, 0) -> Vasquezborough | P262: =VLOOKUP(E262, 'Cleaned Stoer_ Dim'!$A:$E, 5, 0) -> Online | Q262: =VLOOKUP(D262, 'Cleaned Product Dim Dataset'!$A:$G, 2, 0) -> Face Foundation Kit | R262: =VLOOKUP(D262, 'Cleaned Product Dim Dataset'!$A:$G, 3, 0) -> Beauty | S262: =VLOOKUP(D262, 'Cleaned Product Dim Dataset'!$A:$G, 4, 0) -> Makeup | T262: =VLOOKUP(D262, 'Cleaned Product Dim Dataset'!$A:$G, 5, 0) -> Taylor-Elliott
A263: SALE261 | B263: 45742 | C263: CUST1333 | D263: PROD0 | E263: STORE8 | F263: 4 | G263: 849.21 | H263: 0.07 | I263: Credit Card | J263: 3159.06 | K263: =VLOOKUP(C263,'Cleaned Customer_Dim'!$A$2:$H$501,4,0) -> Female | L263: =VLOOKUP(C263, 'Cleaned Customer_Dim'!$A:$F, 6, FALSE) -> Georgia | M263: =VLOOKUP(E263, 'Cleaned Stoer_ Dim'!$A$1:$E$21, 2, 0) -> Bean, Jones and Park | N263: =VLOOKUP(E263, 'Cleaned Stoer_ Dim'!$A:$E,3, 0) -> West | O263: =VLOOKUP(E263, 'Cleaned Stoer_ Dim'!$A:$E, 4, 0) -> Thompsonborough | P263: =VLOOKUP(E263, 'Cleaned Stoer_ Dim'!$A:$E, 5, 0) -> Online | Q263: =VLOOKUP(D263, 'Cleaned Product Dim Dataset'!$A:$G, 2, 0) -> Brother Laser Printer | R263: =VLOOKUP(D263, 'Cleaned Product Dim Dataset'!$A:$G, 3, 0) -> Electronics | S263: =VLOOKUP(D263, 'Cleaned Product Dim Dataset'!$A:$G, 4, 0) -> Computer | T263: =VLOOKUP(D263, 'Cleaned Product Dim Dataset'!$A:$G, 5, 0) -> Hunt Inc
A264: SALE262 | B264: 45713 | C264: CUST1209 | D264: PROD42 | E264: STORE7 | F264: 3 | G264: 553.12 | H264: 0.28 | I264: COD | J264: 1194.74 | K264: =VLOOKUP(C264,'Cleaned Customer_Dim'!$A$2:$H$501,4,0) -> Female | L264: =VLOOKUP(C264, 'Cleaned Customer_Dim'!$A:$F, 6, FALSE) -> Maine | M264: =VLOOKUP(E264, 'Cleaned Stoer_ Dim'!$A$1:$E$21, 2, 0) -> Martinez-Mullins | N264: =VLOOKUP(E264, 'Cleaned Stoer_ Dim'!$A:$E,3, 0) -> South | O264: =VLOOKUP(E264, 'Cleaned Stoer_ Dim'!$A:$E, 4, 0) -> Williamsfurt | P264: =VLOOKUP(E264, 'Cleaned Stoer_ Dim'!$A:$E, 5, 0) -> Online | Q264: =VLOOKUP(D264, 'Cleaned Product Dim Dataset'!$A:$G, 2, 0) -> Smart Home WiFi Camera | R264: =VLOOKUP(D264, 'Cleaned Product Dim Dataset'!$A:$G, 3, 0) -> Electronics | S264: =VLOOKUP(D264, 'Cleaned Product Dim Dataset'!$A:$G, 4, 0) -> Accessories | T264: =VLOOKUP(D264, 'Cleaned Product Dim Dataset'!$A:$G, 5, 0) -> Holmes LLC
A265: SALE263 | B265: 45826 | C265: CUST1282 | D265: PROD91 | E265: STORE9 | F265: 2 | G265: 903.08 | H265: 0.18 | I265: COD | J265: 1481.05 | K265: =VLOOKUP(C265,'Cleaned Customer_Dim'!$A$2:$H$501,4,0) -> Female | L265: =VLOOKUP(C265, 'Cleaned Customer_Dim'!$A:$F, 6, FALSE) -> New Jersey | M265: =VLOOKUP(E265, 'Cleaned Stoer_ Dim'!$A$1:$E$21, 2, 0) -> Moore, Padilla and Butler | N265: =VLOOKUP(E265, 'Cleaned Stoer_ Dim'!$A:$E,3, 0) -> South | O265: =VLOOKUP(E265, 'Cleaned Stoer_ Dim'!$A:$E, 4, 0) -> East Johnstad | P265: =VLOOKUP(E265, 'Cleaned Stoer_ Dim'!$A:$E, 5, 0) -> Flagship | Q265: =VLOOKUP(D265, 'Cleaned Product Dim Dataset'!$A:$G, 2, 0) -> Women's High Heels | R265: =VLOOKUP(D265, 'Cleaned Product Dim Dataset'!$A:$G, 3, 0) -> Clothing | S265: =VLOOKUP(D265, 'Cleaned Product Dim Dataset'!$A:$G, 4, 0) -> Footwear | T265: =VLOOKUP(D265, 'Cleaned Product Dim Dataset'!$A:$G, 5, 0) -> Smith-Charles
A266: SALE264 | B266: 45648 | C266: CUST1478 | D266: PROD16 | E266: STORE11 | F266: 4 | G266: 640.23 | H266: 0.06 | I266: COD | J266: 2407.26 | K266: =VLOOKUP(C266,'Cleaned Customer_Dim'!$A$2:$H$501,4,0) -> Male | L266: =VLOOKUP(C266, 'Cleaned Customer_Dim'!$A:$F, 6, FALSE) -> South Dakota | M266: =VLOOKUP(E266, 'Cleaned Stoer_ Dim'!$A$1:$E$21, 2, 0) -> Aguirre-Keller | N266: =VLOOKUP(E266, 'Cleaned Stoer_ Dim'!$A:$E,3, 0) -> South | O266: =VLOOKUP(E266, 'Cleaned Stoer_ Dim'!$A:$E, 4, 0) -> Lake Michael | P266: =VLOOKUP(E266, 'Cleaned Stoer_ Dim'!$A:$E, 5, 0) -> Online | Q266: =VLOOKUP(D266, 'Cleaned Product Dim Dataset'!$A:$G, 2, 0) -> Beard Grooming Kit | R266: =VLOOKUP(D266, 'Cleaned Product Dim Dataset'!$A:$G, 3, 0) -> Beauty | S266: =VLOOKUP(D266, 'Cleaned Product Dim Dataset'!$A:$G, 4, 0) -> Grooming | T266: =VLOOKUP(D266, 'Cleaned Product Dim Dataset'!$A:$G, 5, 0) -> Erickson-Green
A267: SALE265 | B267: 45836 | C267: CUST1141 | D267: PROD21 | E267: STORE6 | F267: 1 | G267: 518 | H267: 0.25 | I267: Credit Card | J267: 388.5 | K267: =VLOOKUP(C267,'Cleaned Customer_Dim'!$A$2:$H$501,4,0) -> Male | L267: =VLOOKUP(C267, 'Cleaned Customer_Dim'!$A:$F, 6, FALSE) -> California | M267: =VLOOKUP(E267, 'Cleaned Stoer_ Dim'!$A$1:$E$21, 2, 0) -> Benson-Elliott | N267: =VLOOKUP(E267, 'Cleaned Stoer_ Dim'!$A:$E,3, 0) -> East | O267: =VLOOKUP(E267, 'Cleaned Stoer_ Dim'!$A:$E, 4, 0) -> Port Josephberg | P267: =VLOOKUP(E267, 'Cleaned Stoer_ Dim'!$A:$E, 5, 0) -> Online | Q267: =VLOOKUP(D267, 'Cleaned Product Dim Dataset'!$A:$G, 2, 0) -> Multi-Purpose Storage Box | R267: =VLOOKUP(D267, 'Cleaned Product Dim Dataset'!$A:$G, 3, 0) -> Home | S267: =VLOOKUP(D267, 'Cleaned Product Dim Dataset'!$A:$G, 4, 0) -> Storage | T267: =VLOOKUP(D267, 'Cleaned Product Dim Dataset'!$A:$G, 5, 0) -> Gardner-Montes
A268: SALE266 | B268: 45437 | C268: CUST1433 | D268: PROD64 | E268: STORE4 | F268: 4 | G268: 779.25 | H268: 0.25 | I268: Credit Card | J268: 2337.75 | K268: =VLOOKUP(C268,'Cleaned Customer_Dim'!$A$2:$H$501,4,0) -> Female | L268: =VLOOKUP(C268, 'Cleaned Customer_Dim'!$A:$F, 6, FALSE) -> New York | M268: =VLOOKUP(E268, 'Cleaned Stoer_ Dim'!$A$1:$E$21, 2, 0) -> Alexander Group | N268: =VLOOKUP(E268, 'Cleaned Stoer_ Dim'!$A:$E,3, 0) -> South | O268: =VLOOKUP(E268, 'Cleaned Stoer_ Dim'!$A:$E, 4, 0) -> Port Sharon | P268: =VLOOKUP(E268, 'Cleaned Stoer_ Dim'!$A:$E, 5, 0) -> Online | Q268: =VLOOKUP(D268, 'Cleaned Product Dim Dataset'!$A:$G, 2, 0) -> Matte Lipstick Set | R268: =VLOOKUP(D268, 'Cleaned Product Dim Dataset'!$A:$G, 3, 0) -> Beauty | S268: =VLOOKUP(D268, 'Cleaned Product Dim Dataset'!$A:$G, 4, 0) -> Makeup | T268: =VLOOKUP(D268, 'Cleaned Product Dim Dataset'!$A:$G, 5, 0) -> Zhang Inc
A269: SALE267 | B269: 45807 | C269: CUST1118 | D269: PROD83 | E269: STORE7 | F269: 2 | G269: 467.75 | H269: 0.26 | I269: Credit Card | J269: 692.27 | K269: =VLOOKUP(C269,'Cleaned Customer_Dim'!$A$2:$H$501,4,0) -> Male | L269: =VLOOKUP(C269, 'Cleaned Customer_Dim'!$A:$F, 6, FALSE) -> Nebraska | M269: =VLOOKUP(E269, 'Cleaned Stoer_ Dim'!$A$1:$E$21, 2, 0) -> Martinez-Mullins | N269: =VLOOKUP(E269, 'Cleaned Stoer_ Dim'!$A:$E,3, 0) -> South | O269: =VLOOKUP(E269, 'Cleaned Stoer_ Dim'!$A:$E, 4, 0) -> Williamsfurt | P269: =VLOOKUP(E269, 'Cleaned Stoer_ Dim'!$A:$E, 5, 0) -> Online | Q269: =VLOOKUP(D269, 'Cleaned Product Dim Dataset'!$A:$G, 2, 0) -> Hydrating Face Cleanser | R269: =VLOOKUP(D269, 'Cleaned Product Dim Dataset'!$A:$G, 3, 0) -> Beauty | S269: =VLOOKUP(D269, 'Cleaned Product Dim Dataset'!$A:$G, 4, 0) -> Skincare | T269: =VLOOKUP(D269, 'Cleaned Product Dim Dataset'!$A:$G, 5, 0) -> Butler Group
A270: SALE268 | B270: 45555 | C270: CUST1406 | D270: PROD90 | E270: STORE18 | F270: 3 | G270: 513.98 | H270: 0.06 | I270: Credit Card | J270: 315.25 | K270: =VLOOKUP(C270,'Cleaned Customer_Dim'!$A$2:$H$501,4,0) -> Female | L270: =VLOOKUP(C270, 'Cleaned Customer_Dim'!$A:$F, 6, FALSE) -> Wisconsin | M270: =VLOOKUP(E270, 'Cleaned Stoer_ Dim'!$A$1:$E$21, 2, 0) -> Guerrero-Schmitt | N270: =VLOOKUP(E270, 'Cleaned Stoer_ Dim'!$A:$E,3, 0) -> East | O270: =VLOOKUP(E270, 'Cleaned Stoer_ Dim'!$A:$E, 4, 0) -> East Stevechester | P270: =VLOOKUP(E270, 'Cleaned Stoer_ Dim'!$A:$E, 5, 0) -> Flagship | Q270: =VLOOKUP(D270, 'Cleaned Product Dim Dataset'!$A:$G, 2, 0) -> Gaming Mouse Pad XL | R270: =VLOOKUP(D270, 'Cleaned Product Dim Dataset'!$A:$G, 3, 0) -> Electronics | S270: =VLOOKUP(D270, 'Cleaned Product Dim Dataset'!$A:$G, 4, 0) -> Accessories | T270: =VLOOKUP(D270, 'Cleaned Product Dim Dataset'!$A:$G, 5, 0) -> Sharp, Taylor and Rodriguez
A271: SALE269 | B271: 45803 | C271: CUST1219 | D271: PROD37 | E271: STORE0 | F271: 4 | G271: 747.01 | H271: 0.13 | I271: PayPal | J271: 2599.59 | K271: =VLOOKUP(C271,'Cleaned Customer_Dim'!$A$2:$H$501,4,0) -> Female | L271: =VLOOKUP(C271, 'Cleaned Customer_Dim'!$A:$F, 6, FALSE) -> New Jersey | M271: =VLOOKUP(E271, 'Cleaned Stoer_ Dim'!$A$1:$E$21, 2, 0) -> Rivera-Warner | N271: =VLOOKUP(E271, 'Cleaned Stoer_ Dim'!$A:$E,3, 0) -> East | O271: =VLOOKUP(E271, 'Cleaned Stoer_ Dim'!$A:$E, 4, 0) -> Washingtonfurt | P271: =VLOOKUP(E271, 'Cleaned Stoer_ Dim'!$A:$E, 5, 0) -> Flagship | Q271: =VLOOKUP(D271, 'Cleaned Product Dim Dataset'!$A:$G, 2, 0) -> Men's Casual Sneakers | R271: =VLOOKUP(D271, 'Cleaned Product Dim Dataset'!$A:$G, 3, 0) -> Clothing | S271: =VLOOKUP(D271, 'Cleaned Product Dim Dataset'!$A:$G, 4, 0) -> Footwear | T271: =VLOOKUP(D271, 'Cleaned Product Dim Dataset'!$A:$G, 5, 0) -> Hogan-Lee
A272: SALE270 | B272: 45735 | C272: CUST1101 | D272: PROD89 | E272: STORE12 | F272: 4 | G272: 461.83 | H272: 0.28 | I272: PayPal | J272: 1330.07 | K272: =VLOOKUP(C272,'Cleaned Customer_Dim'!$A$2:$H$501,4,0) -> Male | L272: =VLOOKUP(C272, 'Cleaned Customer_Dim'!$A:$F, 6, FALSE) -> Utah | M272: =VLOOKUP(E272, 'Cleaned Stoer_ Dim'!$A$1:$E$21, 2, 0) -> Thomas, Bridges and Harris | N272: =VLOOKUP(E272, 'Cleaned Stoer_ Dim'!$A:$E,3, 0) -> North | O272: =VLOOKUP(E272, 'Cleaned Stoer_ Dim'!$A:$E, 4, 0) -> Sabrinatown | P272: =VLOOKUP(E272, 'Cleaned Stoer_ Dim'!$A:$E, 5, 0) -> Online | Q272: =VLOOKUP(D272, 'Cleaned Product Dim Dataset'!$A:$G, 2, 0) -> Face Foundation Kit | R272: =VLOOKUP(D272, 'Cleaned Product Dim Dataset'!$A:$G, 3, 0) -> Beauty | S272: =VLOOKUP(D272, 'Cleaned Product Dim Dataset'!$A:$G, 4, 0) -> Makeup | T272: =VLOOKUP(D272, 'Cleaned Product Dim Dataset'!$A:$G, 5, 0) -> Taylor-Elliott
A273: SALE271 | B273: 45750 | C273: CUST1134 | D273: PROD70 | E273: STORE8 | F273: 2 | G273: 105.15 | H273: 0.06 | I273: Credit Card | J273: 197.68 | K273: =VLOOKUP(C273,'Cleaned Customer_Dim'!$A$2:$H$501,4,0) -> Male | L273: =VLOOKUP(C273, 'Cleaned Customer_Dim'!$A:$F, 6, FALSE) -> Washington | M273: =VLOOKUP(E273, 'Cleaned Stoer_ Dim'!$A$1:$E$21, 2, 0) -> Bean, Jones and Park | N273: =VLOOKUP(E273, 'Cleaned Stoer_ Dim'!$A:$E,3, 0) -> West | O273: =VLOOKUP(E273, 'Cleaned Stoer_ Dim'!$A:$E, 4, 0) -> Thompsonborough | P273: =VLOOKUP(E273, 'Cleaned Stoer_ Dim'!$A:$E, 5, 0) -> Online | Q273: =VLOOKUP(D273, 'Cleaned Product Dim Dataset'!$A:$G, 2, 0) -> Kitchen Storage Rack | R273: =VLOOKUP(D273, 'Cleaned Product Dim Dataset'!$A:$G, 3, 0) -> Home | S273: =VLOOKUP(D273, 'Cleaned Product Dim Dataset'!$A:$G, 4, 0) -> Storage | T273: =VLOOKUP(D273, 'Cleaned Product Dim Dataset'!$A:$G, 5, 0) -> Duran Group
... A2001: SALE1999 | B2001: 45267 | C2001: CUST1023 | D2001: PROD76 | E2001: STORE19 | F2001: 3 | G2001: 68.45 | H2001: 0.17 | I2001: PayPal | J2001: 170.44 | K2001: =VLOOKUP(C2001,'Cleaned Customer_Dim'!$A$2:$H$501,4,0) -> Female | L2001: =VLOOKUP(C2001, 'Cleaned Customer_Dim'!$A:$F, 6, FALSE) -> Oregon | M2001: =VLOOKUP(E2001, 'Cleaned Stoer_ Dim'!$A$1:$E$21, 2, 0) -> Mann-Austin | N2001: =VLOOKUP(E2001, 'Cleaned Stoer_ Dim'!$A:$E,3, 0) -> East | O2001: =VLOOKUP(E2001, 'Cleaned Stoer_ Dim'!$A:$E, 4, 0) -> Vasquezborough | P2001: =VLOOKUP(E2001, 'Cleaned Stoer_ Dim'!$A:$E, 5, 0) -> Online | Q2001: =VLOOKUP(D2001, 'Cleaned Product Dim Dataset'!$A:$G, 2, 0) -> Wireless Mouse | R2001: =VLOOKUP(D2001, 'Cleaned Product Dim Dataset'!$A:$G, 3, 0) -> Electronics | S2001: =VLOOKUP(D2001, 'Cleaned Product Dim Dataset'!$A:$G, 4, 0) -> Computer | T2001: =VLOOKUP(D2001, 'Cleaned Product Dim Dataset'!$A:$G, 5, 0) -> Larson Ltd

Sheet Standard Deviation of Sales
A1: Sales
A3: Mean | B3: 1087.2
A4: Standard Error | B4: 0.77291667
A5: Median | B5: 868.98
A6: Mode | B6: 502.11
A7: Standard Deviation | B7: 819.41
A8: Minimum | B8: 18.46
A9: Maximum | B9: 3908.24
A10: Sum | B10: 2175481.7
A11: Count | B11: 2001

Sheet Pivot Chart
A3: Row Labels | B3: Sum of Total_Amount
A4: Female | B4: 1231444.2
A5: COD | B5: 410598.5
A6: Credit Card | B6: 373304.42
A7: PayPal | B7: 447541.26
A8: Male | B8: 942950.33
A9: COD | B9: 291860.78
A10: Credit Card | B10: 341876.22
A11: PayPal | B11: 309213.33
A12: Grand Total | B12: 2174394.5
A24: Count of Unit_Price | B24: Column Labels
B25: 2023 | C25: 2024 | D25: 2025 | E25: Grand Total
A28: Row Labels
A29: Beauty | B29: 33 | C29: 158 | D29: 113 | E29: 304
A30: Clothing | B30: 37 | C30: 181 | D30: 116 | E30: 334
A31: Electronics | B31: 49 | C31: 199 | D31: 206 | E31: 454
A32: Home | B32: 49 | C32: 203 | D32: 158 | E32: 410
A33: Sports | B33: 49 | C33: 258 | D33: 191 | E33: 498
A34: Grand Total | B34: 217 | C34: 999 | D34: 784 | E34: 2000
A47: Row Labels | B47: Sum of Total_Amount
A48: Flagship | B48: 848576.65
A49: Bensonhaven | B49: 122176.52
A50: Danielmouth | B50: 101060.64
A51: East Jenniferstad | B51: 99679.06
A52: East Johnstad | B52: 110102.44
A53: East Stevechester | B53: 104313.05
A54: Johnsonville | B54: 114401.46
A55: New Jimmymouth | B55: 111704.93
A56: Washingtonfurt | B56: 85138.55
A57: Online | B57: 914253.45
A58: East Davidville | B58: 109791.72
A59: Lake Michael | B59: 93048.13
... A71: Grand Total | B71: 2174394.5

Sheet Slicer Dashboard
A3: Row Labels | B3: Sum of Total_Amount
A4: Female | B4: 1231444.2
A5: COD | B5: 410598.5
A6: Credit Card | B6: 373304.42
A7: PayPal | B7: 447541.26
A8: Male | B8: 942950.33
A9: COD | B9: 291860.78
A10: Credit Card | B10: 341876.22
A11: PayPal | B11: 309213.33
A12: Grand Total | B12: 2174394.5
A24: Count of Unit_Price | B24: Column Labels
B25: 2023 | C25: 2024 | D25: 2025 | E25: Grand Total
A28: Row Labels
A29: Beauty | B29: 33 | C29: 158 | D29: 113 | E29: 304
A30: Clothing | B30: 37 | C30: 181 | D30: 116 | E30: 334
A31: Electronics | B31: 49 | C31: 199 | D31: 206 | E31: 454
A32: Home | B32: 49 | C32: 203 | D32: 158 | E32: 410
A33: Sports | B33: 49 | C33: 258 | D33: 191 | E33: 498
A34: Grand Total | B34: 217 | C34: 999 | D34: 784 | E34: 2000
A47: Row Labels | B47: Sum of Total_Amount
A48: Flagship | B48: 848576.65
A49: Bensonhaven | B49: 122176.52
A50: Danielmouth | B50: 101060.64
A51: East Jenniferstad | B51: 99679.06
A52: East Johnstad | B52: 110102.44
A53: East Stevechester | B53: 104313.05
A54: Johnsonville | B54: 114401.46
A55: New Jimmymouth | B55: 111704.93
A56: Washingtonfurt | B56: 85138.55
A57: Online | B57: 914253.45
A58: East Davidville | B58: 109791.72
A59: Lake Michael | B59: 93048.13
... A71: Grand Total | B71: 2174394.5
